<?xml version='1.0' encoding='utf-8'?>
<!-- FreeCAD DocumentObject -->
<Document SchemaVersion="4" FileVersion="2">
<Object name="Body" Extensions="True">
  <Extensions Count="1">
    <Extension type="App::OriginGroupExtension" name="OriginGroupExtension">
    </Extension>
  </Extensions>
  <Properties Count="21" TransientCount="2">
    <_Property name="_ElementMapVersion" type="App::PropertyString" status="234881024"/>
    <_Property name="_GroupTouched" type="App::PropertyBool" status="100663425"/>
    <Property name="AutoGroupSolids" type="App::PropertyBool" status="134217728">
      <Bool value="false"/>
    </Property>
    <Property name="BaseFeature" type="App::PropertyLink">
      <Link value=""/>
    </Property>
    <Property name="ClaimAllChildren" type="App::PropertyBool" status="8">
      <Bool value="false"/>
    </Property>
    <Property name="ColoredElements" type="App::PropertyLinkSubHidden" status="218103808">
      <LinkSub value="" count="0">
      </LinkSub>
    </Property>
    <Property name="ExportMode" type="App::PropertyEnumeration" status="8">
      <Integer value="0"/>
    </Property>
    <Property name="ExpressionEngine" type="App::PropertyExpressionEngine" status="67108864">
      <ExpressionEngine count="0"></ExpressionEngine>
    </Property>
    <Property name="FixShape" type="App::PropertyEnumeration">
      <Integer value="0"/>
    </Property>
    <Property name="Group" type="App::PropertyLinkList">
      <LinkList count="7">
        <Link value="Sketch"/>
        <Link value="Boolean"/>
        <Link value="Sketch002"/>
        <Link value="Sketch001"/>
        <Link value="Pad"/>
        <Link value="Sketch003"/>
        <Link value="Pad001"/>
      </LinkList>
    </Property>
    <Property name="InvalidShape" type="App::PropertyBool" status="67108864">
      <Bool value="false"/>
    </Property>
    <Property name="Label" type="App::PropertyString" status="134217728">
      <String value="Body"/>
    </Property>
    <Property name="Label2" type="App::PropertyString" status="128">
      <String value=""/>
    </Property>
    <Property name="Origin" type="App::PropertyLink" status="67108864">
      <Link value="Origin001"/>
    </Property>
    <Property name="Placement" type="App::PropertyPlacement" status="8388608">
      <PropertyPlacement Px="0" Py="0" Pz="0" Q0="0" Q1="0" Q2="0" Q3="1" A="0" Ox="0" Oy="0" Oz="1"/>
    </Property>
    <Property name="Shape" type="Part::PropertyPartShape">
      <Part HasherIndex="0" ElementMap="1.15.70200.4" brep="1">
<![CDATA[

CASCADE Topology V1, (c) Matra-Datavision
Locations 41
1
              1               0               0               0 
              0               1               0               0 
              0               0               1               0 
1
              1               0               0               0 
              0               1               0               0 
              0               0               1               0 
1
              1               0               0               0 
              0               1               0               0 
              0               0               1               0 
1
              1               0               0               0 
              0               1               0               0 
              0               0               1               0 
1
              1               0               0               0 
              0               1               0               0 
              0               0               1               0 
1
              1               0               0               0 
              0               1               0               0 
              0               0               1               0 
1
              1               0               0               0 
              0               1               0               0 
              0               0               1               0 
1
              1               0               0               0 
              0               1               0               0 
              0               0               1               0 
1
              1               0               0               0 
              0               1               0               0 
              0               0               1               0 
1
              1               0               0               0 
              0               1               0           50.06 
              0               0               1               0 
1
              1               0               0               0 
              0               1               0               0 
              0               0               1               0 
2  2 1 3 1 4 1 5 1 6 1 7 1 8 1 9 1 10 1 11 1 0
2  11 -1 10 -1 9 -1 8 -1 7 -1 6 -1 5 -1 4 -1 3 -1 2 -1 0
1
              1               0               0               0 
              0               1               0               0 
              0               0               1               0 
1
2.22044604925031e-16 -3.33066907387547e-16               1               0 
              1 3.33066907387547e-16 -2.22044604925031e-16               0 
-3.33066907387547e-16               1 3.33066907387547e-16               0 
2  14 1 15 1 0
2  11 -1 10 -1 9 -1 8 -1 7 -1 6 -1 5 -1 4 -1 3 -1 2 -1 15 -1 14 -1 0
1
              1               0               0            2.45 
              0               1               0 -8.1601392309949e-16 
              0               0               1 9.52016243616072e-16 
2  14 1 15 1 18 1 0
2  11 -1 10 -1 9 -1 8 -1 7 -1 6 -1 5 -1 4 -1 3 -1 2 -1 18 -1 15 -1 14 -1 0
2  14 1 15 1 2 1 3 1 4 1 5 1 6 1 7 1 8 1 9 1 10 1 11 1 0
1
              1               0               0               0 
              0               1               0               0 
              0               0               1               0 
1
2.22044604925031e-16 -3.33066907387547e-16               1               0 
              1 3.33066907387547e-16 -2.22044604925031e-16               0 
-3.33066907387547e-16               1 3.33066907387547e-16               0 
2  22 1 23 1 0
2  23 -1 22 -1 0
1
              1               0               0               0 
              0               1               0               0 
              0               0               1               0 
1
2.22044604925031e-16 -3.33066907387547e-16               1               0 
              1 3.33066907387547e-16 -2.22044604925031e-16               0 
-3.33066907387547e-16               1 3.33066907387547e-16               0 
2  26 1 27 1 2 1 3 1 4 1 5 1 6 1 7 1 8 1 9 1 10 1 11 1 0
2  11 -1 10 -1 9 -1 8 -1 7 -1 6 -1 5 -1 4 -1 3 -1 2 -1 27 -1 26 -1 0
2  14 1 15 1 18 1 2 1 3 1 4 1 5 1 6 1 7 1 8 1 9 1 10 1 11 1 0
1
              1               0               0            2.45 
              0               1               0 -8.1601392309949e-16 
              0               0               1 9.52016243616072e-16 
2  22 1 23 1 31 1 0
2  31 -1 23 -1 22 -1 0
2  2 -1 0
2  11 -1 10 -1 9 -1 8 -1 7 -1 6 -1 5 -1 4 -1 3 -1 0
1
              1               0               0             1.5 
              0               1               0 -4.9960036108132e-16 
              0               0               1 5.82867087928207e-16 
2  26 1 27 1 36 1 2 1 0
2  11 -1 10 -1 9 -1 8 -1 7 -1 6 -1 5 -1 4 -1 3 -1 2 -1 36 -1 27 -1 26 -1 0
2  26 1 27 1 2 1 0
2  26 1 27 1 36 1 0
2  3 1 4 1 5 1 6 1 7 1 8 1 9 1 10 1 11 1 0
Curve2ds 0
Curves 117
1 -6.9983899285984274e-15 -21.266492276468234 6.8343026654407213 1 -3.3306690738754696e-16 3.8857805861880479e-16 
1 -1.3437637144077918e-15 -5.6506413407306954e-15 4.0345158423206122 1 -3.3306690738754696e-16 3.8857805861880479e-16 
1 -21.266492276468238 6.8343026654407142 -5.242595108778233e-31 0.99144486137381049 -0.13052619222005141 2.4441002838126956e-32 
1 -21.266492276468238 6.8343026654407142 -5.242595108778233e-31 0.99144486137381049 -0.13052619222005141 2.4441002838126956e-32 
1 -5.7934505804417055e-15 -21.788597045348443 2.8685232199454784 1 -3.3306690738754696e-16 3.8857805861880479e-16 
1 -21.266492276468238 6.8343026654407142 -5.242595108778233e-31 -0.1305261922200511 -0.99144486137381049 -3.2177190671800317e-33 
1 -21.266492276468238 6.8343026654407142 -5.242595108778233e-31 -0.1305261922200511 -0.99144486137381049 -3.2177190671800317e-33 
1 2.4458298227408098e-15 21.266492276468238 6.8343026654407124 1 -3.3306690738754696e-16 3.8857805861880479e-16 
1 -6.8833827526759706e-15 4.0345158423206122 -1.6968848591433285e-46 0.99144486137381049 0.13052619222005157 2.4441002838126956e-32 
1 -6.8833827526759706e-15 4.0345158423206122 -1.6968848591433285e-46 0.99144486137381049 0.13052619222005157 2.4441002838126956e-32 
1 21.266492276468234 6.8343026654407195 5.2425951087782321e-31 0.13052619222005024 -0.99144486137381072 3.2177190671800112e-33 
1 0 0 0 0.99144486137381038 0.13052619222005166 2.4441002838126954e-32 
1 53.160086999999997 -1.598924 6.5524866175699479e-31 0 1 0 
1 47.050086999999998 -1.598924 5.7993709721167642e-31 1 0 1.2325951644078288e-32 
1 47.050086999999998 0.3962625639707904 5.7993709721167642e-31 0 -1 0 
1 0 0 0 -0.99144486137381049 0.13052619222005138 -2.4441002838126956e-32 
1 -4.3104742023923473e-16 -2.2139729122391949 2.8634789129665199 -4.347395517580507e-17 -0.99144486137381049 0.13052619222005157 
1 -6.7977222325703085e-16 -4.2416658178913931 3.610250199759018 -3.3021747382305028e-16 0.13052619222005216 0.99144486137381049 
1 5.5171163744236735e-17 -2.4228148197912773 1.2771671347684239 -4.3473955175805095e-17 -0.99144486137381049 0.13052619222005166 
1 -1.1416885323015187 1.1085036592955289 -2.8144795283494436e-32 0.13052619222005069 0.9914448613738106 3.2177190671800222e-33 
1 -4.3104742023923493e-16 0.23108318949156836 2.6024265285264176 4.3473955175804996e-17 -0.99144486137381049 -0.13052619222005135 
1 0.93284662474942515 2.6948154374936251 2.2996444776006097e-32 0.13052619222005185 -0.99144486137381038 3.2177190671800509e-33 
1 5.5171163744236587e-17 0.43992509704365046 1.0161147503283208 4.3473955175804996e-17 -0.99144486137381049 -0.13052619222005135 
1 -6.7977222325703007e-16 4.2416658178913824 3.6102501997590153 -3.3021747382305028e-16 -0.13052619222005146 0.99144486137381049 
1 -8.7513663008929814e-16 -9.9968150740236084 3.8881095218939281 -4.3473955175805015e-17 -0.99144486137381049 0.13052619222005141 
1 -19.483418467717012 3.5232382153664776 -4.8030334778884309e-31 0.1305261922200506 0.9914448613738106 3.2177190671800194e-33 
1 -3.8891804610582647e-16 -10.205656981575689 2.3017977436958308 -4.3473955175805015e-17 -0.99144486137381049 0.13052619222005141 
1 -9.3409486103549439e-16 -15.945991649741018 4.3442507596345861 3.3021747382305023e-16 -0.13052619222005318 -0.99144486137381027 
1 -1.378184070885555e-15 15.945991649741009 4.3442507596345763 3.3021747382305023e-16 0.13052619222005252 -0.99144486137381027 
1 -1.6687344118079438e-16 8.2227672588280658 2.0407453592557223 4.3473955175805021e-17 -0.99144486137381049 -0.13052619222005143 
1 19.274576560164924 5.1095499935645812 4.7515499728135496e-31 0.13052619222005285 -0.99144486137381027 3.2177190671800755e-33 
1 -8.7513663008929755e-16 9.9968150740236048 3.8881095218939237 -4.3473955175805015e-17 0.99144486137381049 0.13052619222005141 
1 21.266492276468234 6.8343026654407195 5.2425951087782321e-31 0.13052619222005024 -0.99144486137381072 3.2177190671800112e-33 
1 0 0 0 0.99144486137381038 0.13052619222005166 2.4441002838126954e-32 
1 53.160086999999997 -1.598924 6.5524866175699479e-31 0 1 0 
1 2.449999999999998 25.031084686126825 1.1102230246251565e-14 -2.2704704898485232e-16 -1 -4.4408920985006262e-16 
1 47.050086999999998 0.3962625639707904 5.7993709721167642e-31 0 -1 0 
1 0 0 0 -0.99144486137381049 0.13052619222005138 -2.4441002838126956e-32 
1 2.4499999999999997 0.23108318949156795 2.6024265285264185 4.3473955175804996e-17 -0.99144486137381049 -0.13052619222005135 
1 2.4499999999999993 4.2416658178913815 3.6102501997590162 -3.3021747382305028e-16 -0.13052619222005146 0.99144486137381049 
1 2.4499999999999993 0.27588637239613939 3.0881454308788103 -3.3021747382305028e-16 -0.13052619222005121 0.99144486137381049 
1 2.4500000000000002 0.43992509704365002 1.0161147503283217 4.3473955175804996e-17 -0.99144486137381049 -0.13052619222005135 
1 2.4499999999999984 15.945991649741007 4.3442507596345772 3.3021747382305023e-16 0.13052619222005252 -0.99144486137381027 
1 2.4499999999999993 9.996815074023603 3.8881095218939246 -4.3473955175805015e-17 0.99144486137381049 0.13052619222005141 
1 2.4500000000000002 8.2227672588280658 2.0407453592557232 4.3473955175805021e-17 -0.99144486137381049 -0.13052619222005143 
1 2.4499999999999984 19.911771095236254 4.8663555285147631 3.3021747382305033e-16 0.13052619222005032 -0.9914448613738106 
1 2.4500000000000002 -2.2139729122391949 2.8634789129665208 -4.347395517580507e-17 -0.99144486137381049 0.13052619222005157 
1 2.4499999999999993 -0.27588637239615232 3.0881454308788117 -3.3021747382305028e-16 0.13052619222005163 0.99144486137381049 
1 2.4499999999999997 -4.2416658178913949 3.6102501997590188 -3.3021747382305028e-16 0.13052619222005216 0.99144486137381049 
1 2.4500000000000002 -2.4228148197912778 1.2771671347684248 -4.3473955175805095e-17 -0.99144486137381049 0.13052619222005166 
1 2.4499999999999993 -9.9968150740236084 3.888109521893929 -4.3473955175805015e-17 -0.99144486137381049 0.13052619222005141 
1 2.4499999999999993 -15.945991649741021 4.3442507596345861 3.3021747382305023e-16 -0.13052619222005318 -0.99144486137381027 
1 2.4499999999999984 -19.807350141460219 5.6595114176138219 -3.3021747382305028e-16 0.13052619222005096 0.99144486137381049 
1 2.4499999999999997 -10.205656981575689 2.3017977436958317 -4.3473955175805015e-17 -0.99144486137381049 0.13052619222005141 
1 1.031523603290814e-14 47.050086999999998 0.39626256397077475 1 -3.3306690738754696e-16 3.8857805861880479e-16 
1 3.8826302651684901e-15 21.788597045348435 2.8685232199454695 1 -3.3306690738754696e-16 3.8857805861880479e-16 
1 1.1667974521138468e-14 53.160086999999997 0.40813419628821884 1 -3.3306690738754696e-16 3.8857805861880479e-16 
1 1.3000000000000151 53.160086999999997 2.3572274576721953e-14 -1 3.3306690738754711e-16 1.4791141972893978e-31 
1 1.5 53.160086999999997 -0.79946200000001777 0 -3.3306690738754696e-16 -1 
1 1.2336459187523019e-14 53.160086999999997 -1.5989240000000178 1 -3.3306690738754696e-16 3.8857805861880479e-16 
1 1.5 23.525043499999999 -1.5989240000000073 0 -1 3.3306690738754711e-16 
1 1.0979766651431078e-14 47.050086999999998 -1.5989240000000158 1 -3.3306690738754696e-16 3.8857805861880479e-16 
1 1.5 47.050086999999998 0.19813128198537955 0 3.3306690738754696e-16 1 
1 1.3000000000000129 47.050086999999998 2.0883314411079821e-14 1 -3.3306690738754711e-16 -1.4791141972893978e-31 
1 -1.104687403994359e-15 -0.93284662474943669 2.6948154374936264 1 -3.3306690738754696e-16 3.8857805861880479e-16 
8 2.4465894629054543 3.28097546470558
1 -0.82000000000000117 -2.6480462349261282 2.9206257500343149 0.70710678118654768 0.7010573846499778 -0.092295955641256991 
1 -0.93284662474943758 2.694815437493626 -2.2996444776006404e-32 0.99144486137381049 -0.13052619222005121 2.4441002838126956e-32 
1 -3.2000000000000024 -4.3037591534203914 3.1386044910418001 1 -3.3306690738754696e-16 3.8857805861880479e-16 
1 -3.2000000000000011 -0.33797970792514925 2.6164997221615938 1 -3.3306690738754696e-16 3.8857805861880479e-16 
1 -3.2000000000000015 -4.5126010609724743 1.5522927128437038 1 -3.3306690738754696e-16 3.8857805861880479e-16 
1 -6.2271166473167026e-16 -1.1416885323015182 1.1085036592955293 1 -3.3306690738754696e-16 3.8857805861880479e-16 
8 2.4465894629054552 3.2809754647055804
1 -0.82000000000000117 -2.8568881424782102 1.3343139718362185 0.70710678118654768 0.7010573846499778 -0.092295955641257046 
1 -0.54682161547723318 1.0301879439634982 -1.3480193580618283e-32 -0.99144486137381049 0.13052619222005124 -2.4441002838126956e-32 
1 -3.2000000000000006 -0.54682161547723174 1.0301879439634971 1 -3.3306690738754696e-16 3.8857805861880479e-16 
1 0.90999999999999959 -1.1416885323015185 1.10850365929553 -3.0123483703918038e-16 0.13052619222005099 0.99144486137381049 
1 0.33797970792513787 2.6164997221615947 8.3318430731298981e-33 0.9914448613738106 0.13052619222005049 2.4441002838126959e-32 
8 -1.8667619023324857 -1.0323759005323592
1 0.17999999999999994 1.6566013735523077 2.7900995578142629 -0.70710678118654746 0.70105738464997824 0.092295955641256824 
1 -3.2000000000000011 0.33797970792513976 2.6164997221615933 1 -3.3306690738754696e-16 3.8857805861880479e-16 
1 -6.9042028349808598e-16 0.93284662474942603 2.6948154374936246 1 -3.3306690738754696e-16 3.8857805861880479e-16 
1 -3.2000000000000002 4.3037591534203816 3.1386044910417987 1 -3.3306690738754696e-16 3.8857805861880479e-16 
1 0.90999999999999914 0.93284662474942581 2.6948154374936251 3.5920011060692032e-16 0.13052619222005155 -0.99144486137381049 
1 -1.1570010652701365e-16 1.1416885323015085 1.1085036592955286 1 -3.3306690738754696e-16 3.8857805861880479e-16 
1 0.54682161547722075 1.030187943963498 1.3480193580617977e-32 0.99144486137381049 0.13052619222005157 2.4441002838126956e-32 
8 -1.8667619023324855 -1.0323759005323589
1 0.18000000000000071 1.8654432811043899 1.2037877796161656 -0.70710678118654746 0.70105738464997824 0.092295955641256824 
1 -3.2000000000000002 0.54682161547722175 1.0301879439634962 1 -3.3306690738754696e-16 3.8857805861880479e-16 
1 -3.1999999999999997 4.5126010609724645 1.5522927128437016 1 -3.3306690738754696e-16 3.8857805861880479e-16 
1 -19.869443476989218 5.1878657088966058 -4.8981959898423128e-31 0.99144486137381072 -0.13052619222004977 2.4441002838126962e-32 
8 -1.8667619023324851 -1.0323759005323605
1 0.17999999999999838 -18.550821811362049 5.0142658732439438 -0.70710678118654702 0.70105738464997835 -0.092295955641257421 
1 -3.2000000000000064 -19.869443476989218 5.1878657088966111 1 -3.3306690738754696e-16 3.8857805861880479e-16 
1 -5.9816377518977046e-15 -19.274576560164931 5.1095499935645821 1 -3.3306690738754696e-16 3.8857805861880479e-16 
1 -3.2000000000000051 -15.903664031493971 4.6657609400164057 1 -3.3306690738754696e-16 3.8857805861880479e-16 
1 -5.4996620126350159e-15 -19.483418467717012 3.5232382153664843 1 -3.3306690738754696e-16 3.8857805861880479e-16 
1 0.9099999999999987 -19.483418467717012 3.5232382153664847 -3.0123483703918038e-16 0.13052619222005091 0.99144486137381049 
1 -20.078285384541299 3.6015539306985094 -4.9496794949171933e-31 0.99144486137381027 -0.13052619222005266 2.4441002838126951e-32 
8 -1.8667619023324824 -1.0323759005323605
1 0.17999999999999905 -18.759663718914133 3.4279540950458465 -0.70710678118654702 0.70105738464997835 -0.092295955641257421 
1 -3.200000000000006 -20.078285384541299 3.6015539306985138 1 -3.3306690738754696e-16 3.8857805861880479e-16 
1 -3.2000000000000046 -16.112505939046059 3.0794491618183084 1 -3.3306690738754696e-16 3.8857805861880479e-16 
1 -3.1999999999999984 15.903664031493971 4.6657609400163995 1 -3.3306690738754696e-16 3.8857805861880479e-16 
1 -3.1999999999999975 16.112505939046052 3.0794491618183022 1 -3.3306690738754696e-16 3.8857805861880479e-16 
1 3.1527138998715474e-15 19.483418467717009 3.5232382153664776 1 -3.3306690738754696e-16 3.8857805861880479e-16 
8 2.4465894629054534 3.2809754647055822
1 -0.8199999999999984 17.768218857540315 3.2974279028257887 0.70710678118654702 0.70105738464997835 0.092295955641257504 
1 20.078285384541292 3.6015539306985156 4.9496794949171915e-31 -0.99144486137381027 -0.13052619222005271 -2.4441002838126951e-32 
1 -3.1999999999999971 20.078285384541292 3.6015539306985076 1 -3.3306690738754696e-16 3.8857805861880479e-16 
1 2.5779937229004743e-15 19.274576560164924 5.109549993564575 1 -3.3306690738754696e-16 3.8857805861880479e-16 
1 0.90999999999999825 19.274576560164924 5.1095499935645758 3.5920011060692052e-16 0.13052619222005252 -0.99144486137381027 
1 19.274576560164924 5.1095499935645812 4.7515499728135496e-31 0.99144486137381027 0.13052619222005266 2.4441002838126951e-32 
8 1.0323759005323569 1.8667619023324862
1 0.18000000000000238 18.550821811362042 5.0142658732439385 0.70710678118654702 0.70105738464997835 0.092295955641257491 
1 -3.1999999999999975 19.869443476989211 5.1878657088966058 1 -3.3306690738754696e-16 3.8857805861880479e-16 
1 1.5 0 0 0 1 4.4408920985006262e-16 
1 0.33797970792513787 2.6164997221615947 8.3318430731298981e-33 0.1305261922200518 -0.99144486137381038 3.2177190671800495e-33 
1 19.869443476989211 5.1878657088966129 4.8981959898423111e-31 0.13052619222005066 -0.9914448613738106 3.2177190671800208e-33 
1 -0.33797970792515031 2.6164997221615951 -8.3318430731302047e-33 -0.1305261922200518 -0.99144486137381049 -3.2177190671800495e-33 
1 -20.078285384541299 3.6015539306985094 -4.9496794949171933e-31 0.13052619222005071 0.99144486137381049 3.2177190671800222e-33 
1 1.4999999999999996 -0.55673606409097054 1.0314932058857 -3.0123483703918038e-16 0.13052619222005099 0.99144486137381049 
1 1.4999999999999991 0.34789415653887745 2.6178049840837945 3.5920011060692032e-16 0.13052619222005155 -0.99144486137381049 
1 1.4999999999999987 -20.068370935927561 3.6002486687763149 -3.0123483703918038e-16 0.13052619222005091 0.99144486137381049 
1 1.4999999999999982 19.859529028375473 5.1865604469744069 3.5920011060692052e-16 0.13052619222005252 -0.99144486137381027 
Polygon3D 0
PolygonOnTriangulations 0
Surfaces 41
1 -6.9983899285984274e-15 -21.266492276468234 6.8343026654407213 -3.4177976428442018e-16 0.13052619222005171 0.99144486137381038 2.6361893772450516e-16 0.99144486137381038 -0.13052619222005171 -1 2.1675242995787096e-16 -3.7326496715961517e-16 
1 -6.9983899285984274e-15 -21.266492276468234 6.8343026654407213 3.8093708819482278e-16 0.99144486137381049 -0.13052619222005143 3.0123483703918028e-16 -0.13052619222005143 -0.99144486137381049 -1 3.3835908235470711e-16 -3.4837999884673654e-16 
1 -1.3437637144077918e-15 -5.5396190382681798e-15 4.0345158423206122 -4.2872767463603027e-16 -0.13052619222005124 0.99144486137381049 1.7667102737289516e-16 0.99144486137381049 0.13052619222005124 -1 2.3111977311208678e-16 -4.019996534680467e-16 
1 5.4064917619894956e-17 50.062169372253656 3.2548095062542917 -1 2.2216710140662468e-16 -1.0451332415498664e-15 1.0451332415498664e-15 0 -1 -2.2216710140662468e-16 -1 -2.3219422285884353e-31 
1 2.4500000000000002 50.062169372253649 3.2548095062542921 1 -2.2704704898485277e-16 1.0362048807870267e-15 -1.0362048807870267e-15 0 1 -2.2704704898485277e-16 -1 -2.3526726032639558e-31 
1 0 0 0 3.4177976428442018e-16 -0.13052619222005171 -0.99144486137381049 -2.6361893772450525e-16 -0.99144486137381049 0.13052619222005171 -1 2.1675242995787106e-16 -3.7326496715961512e-16 
1 2.4458298227408098e-15 21.266492276468238 6.8343026654407124 2.7949785945127841e-16 0.99144486137381072 0.13052619222004991 3.5920011060691993e-16 0.13052619222004991 -0.99144486137381072 -1 3.2399173920049154e-16 -3.196453125383051e-16 
1 0 0 0 -4.2872767463603032e-16 -0.13052619222005135 0.99144486137381049 1.7667102737289506e-16 0.99144486137381049 0.13052619222005135 -1 2.3111977311208673e-16 -4.0199965346804665e-16 
1 1.2336459187523019e-14 53.160086999999997 -1.5989240000000178 -3.3306690738754711e-16 -1 3.3306690738754696e-16 -3.3306690738754691e-16 3.3306690738754706e-16 1 -1 3.3306690738754701e-16 -3.3306690738754701e-16 
1 1.0979766651431078e-14 47.050086999999998 -1.5989240000000158 -3.8857805861880469e-16 3.3306690738754711e-16 1 2.2204460492503131e-16 1 -3.3306690738754701e-16 -1 2.2204460492503118e-16 -3.8857805861880479e-16 
1 1.031523603290814e-14 47.050086999999998 0.39626256397077475 3.3306690738754711e-16 1 -3.3306690738754696e-16 3.3306690738754691e-16 -3.3306690738754706e-16 -1 -1 3.3306690738754701e-16 -3.3306690738754701e-16 
1 -3.2000000000000024 -4.3037591534203914 3.1386044910418001 -3.4177976428442023e-16 0.13052619222005157 0.99144486137381049 2.6361893772450516e-16 0.99144486137381049 -0.13052619222005157 -1 2.1675242995787101e-16 -3.7326496715961512e-16 
1 -3.2000000000000024 -4.3037591534203914 3.1386044910418001 3.8093708819482308e-16 0.99144486137381049 -0.13052619222005216 3.0123483703918013e-16 -0.13052619222005216 -0.99144486137381038 -1 3.3835908235470721e-16 -3.4837999884673673e-16 
1 -3.2000000000000015 -4.5126010609724743 1.5522927128437038 -3.4177976428442018e-16 0.13052619222005166 0.99144486137381049 2.6361893772450516e-16 0.99144486137381049 -0.13052619222005166 -1 2.1675242995787096e-16 -3.7326496715961507e-16 
1 -6.2271166473167026e-16 -1.1416885323015182 1.1085036592955293 -3.8093708819482264e-16 -0.99144486137381049 0.13052619222005099 -3.0123483703918038e-16 0.13052619222005099 0.99144486137381049 -1 3.3835908235470716e-16 -3.4837999884673654e-16 
1 -3.2000000000000011 0.33797970792513976 2.6164997221615933 -4.2872767463603032e-16 -0.13052619222005135 0.99144486137381049 1.7667102737289506e-16 0.99144486137381049 0.13052619222005135 -1 2.3111977311208673e-16 -4.0199965346804665e-16 
1 -6.9042028349808598e-16 0.93284662474942603 2.6948154374936246 2.7949785945127772e-16 0.99144486137381049 0.13052619222005155 3.5920011060692032e-16 0.13052619222005155 -0.99144486137381049 -1 3.2399173920049144e-16 -3.1964531253830505e-16 
1 -3.2000000000000002 0.54682161547722175 1.0301879439634962 -4.2872767463603032e-16 -0.13052619222005135 0.99144486137381049 1.7667102737289506e-16 0.99144486137381049 0.13052619222005135 -1 2.3111977311208673e-16 -4.0199965346804665e-16 
1 -3.2000000000000002 4.3037591534203816 3.1386044910417987 2.7949785945127772e-16 0.99144486137381049 0.13052619222005146 3.5920011060692017e-16 0.13052619222005146 -0.99144486137381049 -1 3.2399173920049139e-16 -3.196453125383049e-16 
1 -3.2000000000000064 -19.869443476989218 5.1878657088966111 -3.4177976428442028e-16 0.13052619222005141 0.99144486137381049 2.6361893772450511e-16 0.99144486137381049 -0.13052619222005141 -1 2.1675242995787101e-16 -3.7326496715961512e-16 
1 -5.4996620126350159e-15 -19.483418467717012 3.5232382153664843 -3.8093708819482259e-16 -0.99144486137381049 0.13052619222005091 -3.0123483703918038e-16 0.13052619222005091 0.99144486137381049 -1 3.3835908235470711e-16 -3.4837999884673649e-16 
1 -3.200000000000006 -20.078285384541299 3.6015539306985138 -3.4177976428442028e-16 0.13052619222005141 0.99144486137381049 2.6361893772450511e-16 0.99144486137381049 -0.13052619222005141 -1 2.1675242995787101e-16 -3.7326496715961512e-16 
1 -3.2000000000000046 -16.112505939046059 3.0794491618183084 -3.8093708819482342e-16 -0.99144486137381027 0.13052619222005318 -3.0123483703917998e-16 0.13052619222005318 0.99144486137381027 -1 3.3835908235470716e-16 -3.4837999884673693e-16 
1 -3.1999999999999975 16.112505939046052 3.0794491618183022 -2.7949785945127727e-16 -0.99144486137381027 -0.13052619222005252 -3.5920011060692052e-16 -0.13052619222005252 0.99144486137381027 -1 3.2399173920049134e-16 -3.19645312538305e-16 
1 -3.1999999999999975 16.112505939046052 3.0794491618183022 -4.2872767463603032e-16 -0.13052619222005143 0.99144486137381049 1.7667102737289504e-16 0.99144486137381049 0.13052619222005143 -1 2.3111977311208673e-16 -4.0199965346804665e-16 
1 2.5779937229004743e-15 19.274576560164924 5.109549993564575 2.7949785945127727e-16 0.99144486137381027 0.13052619222005252 3.5920011060692052e-16 0.13052619222005252 -0.99144486137381027 -1 3.2399173920049134e-16 -3.19645312538305e-16 
1 -3.1999999999999975 19.869443476989211 5.1878657088966058 4.2872767463603032e-16 0.13052619222005141 -0.99144486137381049 -1.7667102737289506e-16 -0.99144486137381049 -0.13052619222005141 -1 2.3111977311208673e-16 -4.0199965346804665e-16 
1 2.6000000000000001 0 0 0 -4.4408920985006262e-16 1 -1 0 0 -0 -1 -4.4408920985006262e-16 
1 -3.2000000000000011 0.33797970792513976 2.6164997221615933 2.7949785945127782e-16 0.99144486137381049 0.13052619222005121 3.5920011060692042e-16 0.13052619222005121 -0.99144486137381049 -1 3.2399173920049149e-16 -3.1964531253830529e-16 
1 -3.1999999999999971 20.078285384541292 3.6015539306985076 -2.7949785945127821e-16 -0.9914448613738106 -0.13052619222005032 -3.5920011060692017e-16 -0.13052619222005032 0.9914448613738106 -1 3.2399173920049149e-16 -3.1964531253830524e-16 
1 -3.2000000000000011 -0.33797970792514925 2.6164997221615938 3.8093708819482288e-16 0.99144486137381049 -0.13052619222005163 3.0123483703918023e-16 -0.13052619222005163 -0.99144486137381049 -1 3.3835908235470711e-16 -3.4837999884673654e-16 
1 -3.2000000000000064 -19.869443476989218 5.1878657088966111 3.8093708819482264e-16 0.99144486137381049 -0.13052619222005096 3.0123483703918038e-16 -0.13052619222005096 -0.99144486137381049 -1 3.3835908235470716e-16 -3.4837999884673654e-16 
1 1.5 0 0 -1 0 0 0 4.4408920985006262e-16 -1 0 -1 -4.4408920985006262e-16 
1 1.2049999999999996 -0.84921229819624444 1.0699984325906149 0.70710678118654735 -0.70105738464997813 0.09229595564125706 -3.0531133177191805e-16 0.13052619222005096 0.99144486137381049 0.70710678118654768 0.7010573846499778 -0.092295955641256588 
1 -1.0355139500639786e-15 -5.147397659625723e-15 3.1090268264300538 1 0 3.3306690738754686e-16 -3.3306690738754686e-16 0 1 0 -1 0 
1 -1.0355139500639786e-15 -5.147397659625723e-15 3.1090268264300538 1 0 3.3306690738754686e-16 -3.3306690738754686e-16 0 1 0 -1 0 
1 1.2049999999999992 0.64037039064415158 2.6563102107887095 0.70710678118654779 0.70105738464997769 0.092295955641257421 3.6082248300317578e-16 0.13052619222005149 -0.99144486137381049 -0.70710678118654746 0.70105738464997824 0.092295955641256977 
1 -1.0355139500639786e-15 -5.147397659625723e-15 3.1090268264300538 1 0 3.3306690738754686e-16 -3.3306690738754686e-16 0 1 0 -1 0 
1 1.2049999999999987 -19.775894701822288 3.5617434420713998 -0.70710678118654813 -0.70105738464997758 0.092295955641256436 -3.6082248300317578e-16 0.13052619222005088 0.99144486137381049 -0.70710678118654713 0.70105738464997858 -0.092295955641257088 
1 1.2049999999999983 19.567052794270197 5.1480552202694909 -0.70710678118654802 0.70105738464997736 0.092295955641257643 3.3306690738754691e-16 0.13052619222005254 -0.99144486137381038 0.70710678118654713 0.70105738464997835 0.09229595564125824 
1 -1.0355139500639786e-15 -5.147397659625723e-15 3.1090268264300538 1 0 3.3306690738754686e-16 -3.3306690738754686e-16 0 1 0 -1 0 
Triangulations 0

TShapes 287
Ve
1e-07
-6.99838992859843e-15 28.7935077235318 6.83430266544072
0 0

0101101
*
Ve
1e-07
2.44999999999999 28.7935077235318 6.83430266544072
0 0

0101101
*
Ed
 1e-07 1 1 0
1  1 0 0 2.45
0

0101000
+287 13 -286 13 *
Ve
1.00000000111022e-07
-1.34376371440779e-15 50.06 4.03451584232061
0 0

0101101
*
Ve
1.00000000111022e-07
2.45 50.06 4.03451584232061
0 0

0101101
*
Ed
 1.00000000111022e-07 1 1 0
1  2 0 0 2.45
0

0101000
+284 13 -283 13 *
Ed
 1e-07 1 1 0
1  3 0 0 21.45
0

0101000
+287 17 -284 17 *
Ed
 1e-07 1 1 0
1  4 0 0 21.45
0

0101000
+286 20 -283 20 *
Wi

0101100
+285 0 -282 0 -281 16 +280 19 *
Fa
0  1e-07 1 0

0101000
+279 0 *
Ve
1e-07
-5.79345058044171e-15 28.2714029546516 2.86852321994548
0 0

0101101
*
Ve
1e-07
2.44999999999999 28.2714029546516 2.86852321994548
0 0

0101101
*
Ed
 1e-07 1 1 0
1  5 0 0 2.45
0

0101000
+277 13 -276 13 *
Ed
 1e-07 1 1 0
1  6 0 0 4
0

0101000
+287 17 -277 17 *
Ed
 1e-07 1 1 0
1  7 0 0 4
0

0101000
+286 20 -276 20 *
Wi

0101100
+285 0 -275 0 -274 16 +273 19 *
Fa
0  1e-07 2 0

0101000
+272 0 *
Ve
1e-07
2.44582982274081e-15 71.3264922764682 6.83430266544071
0 0

0101101
*
Ve
1e-07
2.45 71.3264922764682 6.83430266544071
0 0

0101101
*
Ed
 1e-07 1 1 0
1  8 0 0 2.45
0

0101000
+270 13 -269 13 *
Ed
 1e-07 1 1 0
1  9 0 0 21.45
0

0101000
+284 17 -270 17 *
Ed
 1e-07 1 1 0
1  10 0 0 21.45
0

0101000
+283 20 -269 20 *
Wi

0101100
+282 0 -268 0 -267 16 +266 19 *
Fa
0  1e-07 3 0

0101000
+265 0 *
Ve
1e-07
3.88263026516849e-15 71.8485970453484 2.86852321994547
0 0

0101101
*
Ed
 1e-07 1 1 0
1  11 0 0 4
0

0101000
+270 17 -263 17 *
Ve
1.00000011588019e-07
1.16679745211385e-14 53.160087 0.408134196288219
0 0

0101101
*
Ed
 1e-07 1 1 0
1  12 0 3.12683752851804 21.9766099903496
0

0101000
+261 17 -263 17 *
Ve
1e-07
1.2336459187523e-14 53.160087 -1.59892400000002
0 0

0101101
*
Ed
 1e-07 1 1 0
1  13 0 0 2.00705819628824
0

0101000
+259 25 -261 25 *
Ve
1e-07
1.09797666514311e-14 47.050087 -1.59892400000002
0 0

0101101
*
Ed
 1e-07 1 1 0
1  14 0 0 6.11
0

0101000
+257 25 -259 25 *
Ve
1.00000011534612e-07
1.03152360329081e-14 47.050087 0.396262563970775
0 0

0101101
*
Ed
 1e-07 1 1 0
1  15 0 0 1.99518656397079
0

0101000
+255 25 -257 25 *
Ed
 1e-07 1 1 0
1  16 0 3.03588542062669 21.9766099903496
0

0101000
+255 17 -277 17 *
Wi

0101100
+281 21 +267 21 +262 21 -260 21 -258 24 -256 24 -254 24 +253 21 -274 21 *
Ve
1.50000001519068e-07
-1.10468740399436e-15 49.1271533752506 2.69481543749363
0 0

0101101
*
Ve
1.50000002019379e-07
-8.88178419700125e-16 45.7562408465796 3.1386044910418
0 0

0101101
*
Ed
 1.5e-07 1 1 0
1  17 0 -1.2921810757227 2.1078189242773
0

0101000
+251 13 -250 13 *
Ve
1.50000001836003e-07
-4.44089209850063e-16 45.5473989390275 1.55229271284371
0 0

0101101
*
Ed
 1.5e-07 1 1 0
1  18 0 -2.07571552094554 -0.475715520945535
0

0101000
+248 13 -250 13 *
Ve
1.50000000886206e-07
-6.2271166473167e-16 48.9183114676985 1.10850365929553
0 0

0101101
*
Ed
 1.5e-07 1 1 0
1  19 0 -1.29218107572271 2.1078189242773
0

0101000
+246 13 -248 13 *
Ed
 1e-07 1 1 0
1  20 0 0 1.6
0

0101000
+246 29 -251 29 *
Wi

0101100
+249 12 -247 12 -245 12 +244 28 *
Ve
1.50000000930833e-07
-8.88178419700125e-16 54.3637591534204 3.1386044910418
0 0

0101101
*
Ve
1.50000000511664e-07
-6.90420283498086e-16 50.9928466247494 2.69481543749362
0 0

0101101
*
Ed
 1.5e-07 1 1 0
1  21 0 -4.10781892427729 -0.70781892427729
0

0101000
+242 13 -241 13 *
Ve
1.50000000262548e-07
-1.15700106527014e-16 51.2016885323015 1.10850365929553
0 0

0101101
*
Ed
 1e-07 1 1 0
1  22 0 0 1.6
0

0101000
+241 29 -239 29 *
Ve
1.50000000970051e-07
-4.44089209850063e-16 54.5726010609725 1.5522927128437
0 0

0101101
*
Ed
 1.5e-07 1 1 0
1  23 0 -4.10781892427729 -0.707818924277291
0

0101000
+237 13 -239 13 *
Ed
 1.5e-07 1 1 0
1  24 0 -2.07571552094553 -0.475715520945534
0

0101000
+237 13 -242 13 *
Wi

0101100
+240 12 +238 28 -236 12 +235 12 *
Ve
1.50000003673604e-07
-1.33226762955019e-15 34.156335968506 4.66576094001641
0 0

0101101
*
Ve
1.50000004782871e-07
-5.9816377518977e-15 30.7854234398351 5.10954999356458
0 0

0101101
*
Ed
 1.5e-07 1 1 0
1  25 0 5.95781892427729 9.35781892427729
0

0101000
+233 13 -232 13 *
Ve
1.50000004724839e-07
-5.49966201263502e-15 30.576581532283 3.52323821536648
0 0

0101101
*
Ed
 1e-07 1 1 0
1  26 0 0 1.6
0

0101000
+230 29 -232 29 *
Ve
1.50000003599983e-07
-8.88178419700125e-16 33.9474940609539 3.07944916181831
0 0

0101101
*
Ed
 1.5e-07 1 1 0
1  27 0 5.9578189242773 9.35781892427729
0

0101000
+228 13 -230 13 *
Ed
 1.5e-07 1 1 0
1  28 0 -0.324284479054454 1.27571552094555
0

0101000
+233 13 -228 13 *
Wi

0101100
+231 12 -229 28 -227 12 -226 12 *
Ve
1.50000001995885e-07
-1.33226762955019e-15 65.963664031494 4.6657609400164
0 0

0101101
*
Ve
1.50000000581464e-07
-8.88178419700125e-16 66.1725059390461 3.0794491618183
0 0

0101101
*
Ed
 1.5e-07 1 1 0
1  29 0 -0.324284479054457 1.27571552094554
0

0101000
+224 13 -223 13 *
Ve
1.50000003915425e-07
3.15271389987155e-15 69.543418467717 3.52323821536648
0 0

0101101
*
Ed
 1.5e-07 1 1 0
1  30 0 -11.3578189242773 -7.95781892427729
0

0101000
+221 13 -223 13 *
Ve
1.50000003960819e-07
2.57799372290047e-15 69.3345765601649 5.10954999356457
0 0

0101101
*
Ed
 1e-07 1 1 0
1  31 0 0 1.6
0

0101000
+219 29 -221 29 *
Ed
 1.5e-07 1 1 0
1  32 0 5.95781892427729 9.35781892427729
0

0101000
+224 13 -219 13 *
Wi

0101100
+222 12 -220 12 -218 28 -217 12 *
Fa
0  1e-07 4 0

0101000
+252 0 +243 0 +234 0 +225 0 +216 0 *
Ve
1e-07
2.45 71.8485970453484 2.86852321994547
0 0

0101101
*
Ed
 1e-07 1 1 0
1  33 0 0 4
0

0101000
+269 20 -214 20 *
Ve
1.0000001157524e-07
2.45000000000001 53.160087 0.40813419628822
0 0

0101101
*
Ed
 1e-07 1 1 0
1  34 0 3.12683752851804 21.9766099903496
0

0101000
+212 20 -214 20 *
Ve
1.50000007993811e-07
2.45000000000001 53.160087 2.35367281220533e-14
0 0

0101101
*
Ed
 1e-07 1 1 0
1  35 0 1.59892400000004 2.00705819628824
0

0101000
+210 33 -212 33 *
Ve
1.50000007549521e-07
2.45000000000001 47.050087 2.08721928629529e-14
0 0

0101101
*
Ed
 1.5e-07 1 1 0
1  36 0 -28.1290023138732 -22.0190023138732
0

0101000
+210 0 -208 0 *
Ve
1.00000011523631e-07
2.45000000000001 47.050087 0.396262563970776
0 0

0101101
*
Ed
 1e-07 1 1 0
1  37 0 0 0.396262563970755
0

0101000
+206 33 -208 33 *
Ed
 1e-07 1 1 0
1  38 0 3.03588542062669 21.9766099903496
0

0101000
+206 20 -276 20 *
Wi

0101100
-280 30 -266 30 -213 30 +211 30 +209 32 -207 0 +205 32 -204 30 +273 30 *
Ve
1.50000002220446e-07
2.45 54.3637591534204 3.1386044910418
0 0

0101101
*
Ve
1.50000000649741e-07
2.45 50.3979797079251 2.6164997221616
0 0

0101101
*
Ed
 1.5e-07 1 1 0
1  39 0 -4.10781892427729 -0.107818924277289
0

0101000
+202 13 -201 13 *
Ve
1.50000002231521e-07
2.45 54.5726010609725 1.5522927128437
0 0

0101101
*
Ed
 1.5e-07 1 1 0
1  40 0 -2.07571552094553 -0.475715520945534
0

0101000
+199 13 -202 13 *
Ve
1.50000000314018e-07
2.45 50.6068216154772 1.0301879439635
0 0

0101101
*
Ed
 1.5e-07 1 1 0
1  41 0 -2.07571552094553 -0.475715520945534
0

0101000
+197 13 -201 13 *
Ed
 1.5e-07 1 1 0
1  42 0 -4.10781892427729 -0.107818924277288
0

0101000
+199 13 -197 13 *
Wi

0101100
-200 12 -198 12 +196 12 +195 12 *
Ve
1.50000003662053e-07
2.45 65.963664031494 4.6657609400164
0 0

0101101
*
Ve
1.50000003607798e-07
2.45 66.172505939046 3.0794491618183
0 0

0101101
*
Ed
 1.5e-07 1 1 0
1  43 0 -0.324284479054457 1.27571552094554
0

0101000
+193 13 -192 13 *
Ve
1.50000003688882e-07
2.45 69.9294434769892 5.18786570889661
0 0

0101101
*
Ed
 1.5e-07 1 1 0
1  44 0 5.95781892427729 9.95781892427729
0

0101000
+193 13 -190 13 *
Ve
1.50000007174481e-07
2.45 70.1382853845413 3.60155393069851
0 0

0101101
*
Ed
 1.5e-07 1 1 0
1  45 0 -11.9578189242773 -7.95781892427729
0

0101000
+188 13 -192 13 *
Ed
 1.5e-07 1 1 0
1  46 0 -0.324284479054478 1.27571552094552
0

0101000
+190 13 -188 13 *
Wi

0101100
-191 12 +189 12 +187 12 +186 12 *
Ve
1.50000001640164e-07
2.45 49.7220202920749 2.6164997221616
0 0

0101101
*
Ve
1.50000001831027e-07
2.45 45.7562408465796 3.1386044910418
0 0

0101101
*
Ed
 1.5e-07 1 1 0
1  47 0 -1.8921810757227 2.1078189242773
0

0101000
+184 13 -183 13 *
Ve
1.50000000915513e-07
2.45 49.5131783845228 1.0301879439635
0 0

0101101
*
Ed
 1.5e-07 1 1 0
1  48 0 -2.07571552094554 -0.475715520945535
0

0101000
+181 13 -184 13 *
Ve
1.50000002521942e-07
2.45 45.5473989390275 1.55229271284371
0 0

0101101
*
Ed
 1.5e-07 1 1 0
1  49 0 -2.07571552094554 -0.475715520945535
0

0101000
+179 13 -183 13 *
Ed
 1.5e-07 1 1 0
1  50 0 -1.8921810757227 2.1078189242773
0

0101000
+181 13 -179 13 *
Wi

0101100
-182 12 -180 12 +178 12 +177 12 *
Ve
1.50000007174481e-07
2.45 34.156335968506 4.66576094001641
0 0

0101101
*
Ve
1.50000003552714e-07
2.45 30.1905565230108 5.18786570889661
0 0

0101101
*
Ed
 1.5e-07 1 1 0
1  51 0 5.95781892427729 9.9578189242773
0

0101000
+175 13 -174 13 *
Ve
1.50000003580362e-07
2.45 33.9474940609539 3.07944916181831
0 0

0101101
*
Ed
 1.5e-07 1 1 0
1  52 0 -0.324284479054455 1.27571552094555
0

0101000
+175 13 -172 13 *
Ve
1.50000003688882e-07
2.45 29.9817146154587 3.60155393069852
0 0

0101101
*
Ed
 1.5e-07 1 1 0
1  53 0 -2.07571552094553 -0.475715520945528
0

0101000
+170 13 -174 13 *
Ed
 1.5e-07 1 1 0
1  54 0 5.9578189242773 9.9578189242773
0

0101000
+172 13 -170 13 *
Wi

0101100
-173 12 +171 12 +169 12 +168 12 *
Fa
0  1e-07 5 0

0101000
+203 0 +194 0 +185 0 +176 0 +167 0 *
Ed
 1.00000002498002e-07 1 1 0
1  55 0 0 2.45
0

0101000
+255 0 -206 0 *
Wi

0101100
-253 21 -275 12 +204 30 +165 0 *
Fa
0  1e-07 6 12

0101000
+164 0 *
Ed
 1e-07 1 1 0
1  56 0 0 2.45
0

0101000
+263 13 -214 13 *
Wi

0101100
+268 0 -162 0 -262 16 +213 19 *
Fa
0  1e-07 7 0

0101000
+161 0 *
Ed
 1.00000003053113e-07 1 1 0
1  57 0 0 2.45
0

0101000
+261 0 -212 0 *
Wi

0101100
-260 21 -162 12 +211 30 +159 0 *
Fa
0  1e-07 8 12

0101000
+158 0 *
Ve
1.50000000039929e-07
1.5 53.160087 2.36078210313906e-14
0 0

0101101
*
Ed
 1.5e-07 1 1 0
1  58 0 -1.15 -0.199999999999985
0

0101000
+210 0 -156 0 *
Ve
1.50000000222045e-07
1.5 53.160087 -1.59892400000002
0 0

0101101
*
Ed
 1.5e-07 1 1 0
1  59 0 -0.799462000000041 0.799462
0

0101000
+156 0 -154 0 *
Ed
 1e-07 1 1 0
1  60 0 0 1.49999999999999
0

0101000
+259 0 -154 0 *
Wi

0101100
-258 24 -159 0 +209 32 -155 0 -153 0 +152 0 *
Fa
0  1e-07 9 0

0101000
+151 0 *
Ve
1.5e-07
1.5 47.050087 -1.59892400000002
0 0

0101101
*
Ed
 1.5e-07 1 1 0
1  61 0 -29.6350435 -23.5250435
0

0101000
+154 0 -149 0 *
Ed
 1e-07 1 1 0
1  62 0 0 1.49999999999999
0

0101000
+257 0 -149 0 *
Wi

0101100
-256 24 -152 0 -148 0 +147 0 *
Fa
0  1e-07 10 0

0101000
+146 0 *
Ve
1.50000000011122e-07
1.5 47.050087 2.08944359592067e-14
0 0

0101101
*
Ed
 1.5e-07 1 1 0
1  63 0 -1.79705528198539 -0.198131281985359
0

0101000
+149 0 -144 0 *
Ed
 1.5e-07 1 1 0
1  64 0 0.199999999999987 1.15
0

0101000
+144 0 -208 0 *
Wi

0101100
-254 24 -147 0 -143 0 -142 0 +205 32 +165 0 *
Fa
0  1e-07 11 0

0101000
+141 0 *
Ve
1.00000000457757e-07
0.909999999999999 49.1271533752506 2.69481543749363
0 0

0101101
*
Ed
 1.00000000457757e-07 1 1 0
1  65 0 0 0.91
0

0101000
-139 13 +251 13 *
Ve
1.00000000457757e-07
1.5 49.7121058434611 2.6178049840838
0 0

0101101
*
Ed
 1e-07 1 1 0
1  66 0 2.44658946290545 3.28097546470558
0

0101000
+139 35 -137 35 *
Ve
1.00000000993014e-07
1.5 49.7220202920749 2.6164997221616
0 0

0101101
*
Ed
 1.00000000457757e-07 1 1 0
1  67 0 0.589999999999999 0.600000000000001
0

0101000
+137 38 -135 38 *
Ed
 1e-07 1 1 0
1  68 0 3.2 5.65
0

0101000
+250 13 -183 13 *
Ed
 1e-07 1 1 0
1  69 0 4.7 5.65
0

0101000
+135 13 -184 13 *
Wi

0101100
-138 2 -136 0 +249 2 -134 37 +133 2 -132 2 -182 2 *
Fa
0  1e-07 12 0

0101000
+131 34 *
Ed
 1e-07 1 1 0
1  70 0 3.2 5.65
0

0101000
+248 13 -179 13 *
Wi

0101100
+247 0 -129 0 -178 0 +133 0 *
Fa
0  1e-07 13 0

0101000
+128 0 *
Ve
1e-07
0.91 48.9183114676985 1.10850365929553
0 0

0101101
*
Ed
 1e-07 1 1 0
1  71 0 0 0.91
0

0101000
-126 13 +246 13 *
Ve
1.00000000222045e-07
1.5 49.503263935909 1.0314932058857
0 0

0101101
*
Ed
 1e-07 1 1 0
1  72 0 2.44658946290546 3.28097546470558
0

0101000
+126 35 -124 35 *
Ve
1.00000000777156e-07
1.5 49.5131783845228 1.0301879439635
0 0

0101101
*
Ed
 1.00000000222045e-07 1 1 0
1  73 0 0 0.0100000000000002
0

0101000
-124 38 +122 38 *
Ed
 1.00000000055511e-07 1 1 0
1  74 0 4.7 5.65
0

0101000
+122 13 -181 13 *
Wi

0101100
-125 2 -123 0 +245 2 +121 37 +129 2 -120 2 -177 2 *
Fa
0  1e-07 14 0

0101000
+119 34 *
Ed
 1e-07 1 1 0
1  75 0 -2.96171023594379e-16 1.6
0

0101000
+126 35 -139 35 *
Wi

0101100
+125 2 +117 0 -244 39 -138 2 *
Fa
0  1e-07 15 0

0101000
+116 34 *
Ve
1.0000000089509e-07
1.5 50.4078941565389 2.6178049840838
0 0

0101101
*
Ve
1.0000000089509e-07
1.5 50.3979797079251 2.6164997221616
0 0

0101101
*
Ed
 1.0000000089509e-07 1 1 0
1  76 0 0 0.0100000000000009
0

0101000
-114 38 +113 38 *
Ve
1.0000000089509e-07
0.909999999999999 50.9928466247494 2.69481543749362
0 0

0101101
*
Ed
 1e-07 1 1 0
1  77 0 -1.86676190233249 -1.03237590053236
0

0101000
+114 35 -111 35 *
Ed
 1e-07 1 1 0
1  78 0 4.7 5.65
0

0101000
+113 13 -201 13 *
Ed
 1.0000000089509e-07 1 1 0
1  79 0 0 0.91
0

0101000
-111 13 +241 13 *
Ed
 1e-07 1 1 0
1  80 0 3.2 5.65
0

0101000
+242 13 -202 13 *
Wi

0101100
-112 37 -110 0 +109 2 +108 2 -200 2 +240 2 -107 2 *
Fa
0  1e-07 16 0

0101000
+106 34 *
Ve
1.00000000222045e-07
0.91 51.2016885323015 1.10850365929553
0 0

0101101
*
Ed
 1e-07 1 1 0
1  81 0 -1.44210525212643e-15 1.6
0

0101000
+111 35 -104 35 *
Ed
 1.00000000222045e-07 1 1 0
1  82 0 0 0.91
0

0101000
-104 13 +239 13 *
Wi

0101100
+108 2 +103 0 -238 39 -102 2 *
Fa
0  1e-07 17 0

0101000
+101 34 *
Ve
1.00000000444089e-07
1.5 50.616736064091 1.0314932058857
0 0

0101101
*
Ve
1.00000000628037e-07
1.5 50.6068216154772 1.0301879439635
0 0

0101101
*
Ed
 1.00000000444089e-07 1 1 0
1  83 0 0 0.010000000000001
0

0101000
-99 38 +98 38 *
Ed
 1e-07 1 1 0
1  84 0 -1.86676190233249 -1.03237590053236
0

0101000
+99 35 -104 35 *
Ed
 1e-07 1 1 0
1  85 0 4.7 5.65
0

0101000
+98 13 -197 13 *
Ed
 1e-07 1 1 0
1  86 0 3.2 5.65
0

0101000
+237 13 -199 13 *
Wi

0101100
-97 37 -96 0 +95 2 +102 2 -195 2 +236 2 -94 2 *
Fa
0  1e-07 18 0

0101000
+93 34 *
Wi

0101100
+235 0 -94 0 -198 0 +107 0 *
Fa
0  1e-07 19 0

0101000
+91 0 *
Ve
1.00000001776357e-07
1.5 30.2004709716245 5.18656044697441
0 0

0101101
*
Ve
1.00000003662053e-07
1.49999999999999 30.1905565230108 5.18786570889661
0 0

0101101
*
Ed
 1.00000001776357e-07 1 1 0
1  87 0 0 0.0100000000000008
0

0101000
-89 38 +88 38 *
Ve
1.00000000888178e-07
0.909999999999999 30.7854234398351 5.10954999356458
0 0

0101101
*
Ed
 1e-07 1 1 0
1  88 0 -1.86676190233249 -1.03237590053236
0

0101000
+89 35 -86 35 *
Ed
 1e-07 1 1 0
1  89 0 4.7 5.65
0

0101000
+88 13 -174 13 *
Ed
 1.00000000888178e-07 1 1 0
1  90 0 0 0.910000000000005
0

0101000
-86 13 +232 13 *
Ed
 1e-07 1 1 0
1  91 0 3.2 5.65
0

0101000
+233 13 -175 13 *
Wi

0101100
-87 37 -85 0 +84 2 +83 2 -173 2 +231 2 -82 2 *
Fa
0  1e-07 20 0

0101000
+81 34 *
Ve
1.00000000444089e-07
0.91 30.576581532283 3.52323821536648
0 0

0101101
*
Ed
 1.00000000444089e-07 1 1 0
1  92 0 0 0.910000000000005
0

0101000
-79 13 +230 13 *
Ed
 1e-07 1 1 0
1  93 0 6.03281072376869e-17 1.6
0

0101000
+79 35 -86 35 *
Wi

0101100
+78 2 +77 0 -229 39 -83 2 *
Fa
0  1e-07 21 0

0101000
+76 34 *
Ve
1.00000001332268e-07
1.5 29.9916290640724 3.60024866877632
0 0

0101101
*
Ve
1.00000003662053e-07
1.49999999999999 29.9817146154587 3.60155393069852
0 0

0101101
*
Ed
 1.00000001332268e-07 1 1 0
1  94 0 0 0.0100000000000003
0

0101000
-74 38 +73 38 *
Ed
 1e-07 1 1 0
1  95 0 -1.86676190233248 -1.03237590053236
0

0101000
+74 35 -79 35 *
Ed
 1e-07 1 1 0
1  96 0 4.7 5.65
0

0101000
+73 13 -170 13 *
Ed
 1e-07 1 1 0
1  97 0 3.2 5.65
0

0101000
+228 13 -172 13 *
Wi

0101100
-72 37 -71 0 +70 2 +78 2 -168 2 +227 2 -69 2 *
Fa
0  1e-07 22 0

0101000
+68 34 *
Wi

0101100
+226 0 -82 0 -171 0 +69 0 *
Fa
0  1e-07 23 0

0101000
+66 0 *
Ed
 1e-07 1 1 0
1  98 0 3.2 5.65
0

0101000
+224 13 -193 13 *
Ed
 1e-07 1 1 0
1  99 0 3.2 5.65
0

0101000
+223 13 -192 13 *
Wi

0101100
+222 0 -64 0 -191 0 +63 0 *
Fa
0  1e-07 24 0

0101000
+62 0 *
Ve
1.00000001332268e-07
0.909999999999999 69.543418467717 3.52323821536648
0 0

0101101
*
Ed
 1.00000001332268e-07 1 1 0
1  100 0 0 0.909999999999996
0

0101000
-60 13 +221 13 *
Ve
1.00000001332268e-07
1.5 70.1283709359276 3.60024866877631
0 0

0101101
*
Ed
 1e-07 1 1 0
1  101 0 2.44658946290545 3.28097546470558
0

0101000
+60 35 -58 35 *
Ve
1.00000003580362e-07
1.5 70.1382853845413 3.60155393069851
0 0

0101101
*
Ed
 1.00000001332268e-07 1 1 0
1  102 0 0 0.00999999999999703
0

0101000
-58 38 +56 38 *
Ed
 1e-07 1 1 0
1  103 0 4.7 5.65
0

0101000
+56 13 -188 13 *
Wi

0101100
-59 2 -57 0 +220 2 +55 37 +63 2 -54 2 -187 2 *
Fa
0  1e-07 25 0

0101000
+53 34 *
Ve
1.00000001776357e-07
0.909999999999998 69.3345765601649 5.10954999356458
0 0

0101101
*
Ed
 1.00000001776357e-07 1 1 0
1  104 0 0 0.909999999999996
0

0101000
-51 13 +219 13 *
Ed
 1e-07 1 1 0
1  105 0 8.44541315125497e-16 1.6
0

0101000
+51 35 -60 35 *
Wi

0101100
+50 2 +49 0 -218 39 -59 2 *
Fa
0  1e-07 26 0

0101000
+48 34 *
Ve
1.00000000888178e-07
1.5 69.9195290283755 5.18656044697441
0 0

0101101
*
Ve
1.00000003580362e-07
1.5 69.9294434769892 5.18786570889661
0 0

0101101
*
Ed
 1.00000000888178e-07 1 1 0
1  106 0 0.590000000000001 0.600000000000001
0

0101000
+46 38 -45 38 *
Ed
 1e-07 1 1 0
1  107 0 1.03237590053236 1.86676190233249
0

0101000
+51 35 -46 35 *
Ed
 1e-07 1 1 0
1  108 0 4.7 5.65
0

0101000
+45 13 -190 13 *
Wi

0101100
+44 37 +43 0 +42 2 +50 2 -189 2 +217 2 -64 2 *
Fa
0  1e-07 27 0

0101000
+41 34 *
Ed
 1e-07 1 1 0
1  109 0 47.050087 53.160087
0

0101000
+144 0 -156 0 *
Wi

0101100
-39 0 +155 0 -207 0 +142 0 *
Fa
0  1e-07 28 0

0101000
+38 0 *
Ed
 1.00000000444089e-07 1 1 0
1  110 0 0 1.6
0

0101000
+113 38 -98 38 *
Wi

0101100
-95 0 -196 0 +109 0 -36 40 *
Fa
0  1e-07 29 0

0101000
+35 0 *
Ed
 1.00000003580362e-07 1 1 0
1  111 0 0 1.6
0

0101000
+45 38 -56 38 *
Wi

0101100
-42 0 -186 0 +54 0 +33 40 *
Fa
0  1e-07 30 0

0101000
+32 0 *
Ed
 1.00000000777156e-07 1 1 0
1  112 0 0 1.6
0

0101000
+135 38 -122 38 *
Wi

0101100
-120 0 -180 0 +132 0 -30 40 *
Fa
0  1e-07 31 0

0101000
+29 0 *
Ed
 1.00000003662053e-07 1 1 0
1  113 0 0 1.6
0

0101000
+73 38 -88 38 *
Wi

0101100
-70 0 -169 0 +84 0 +27 40 *
Fa
0  1e-07 32 0

0101000
+26 0 *
Wi

0101100
+143 0 +148 0 +153 0 +39 0 *
Fa
0  1e-07 33 0

0101000
+24 0 *
Ed
 1e-07 1 1 0
1  114 0 -6.11096453805829e-16 1.6
0

0101000
+124 35 -137 35 *
Wi

0101100
-123 0 +117 0 -22 0 +136 0 *
Fa
0  1e-07 34 0

0101000
+21 0 *
Wi

0101100
-134 37 -22 0 -30 37 -121 37 *
Fa
0  1e-07 35 36

0101000
+19 34 *
Ed
 1e-07 1 1 0
1  115 0 -1.25897556269017e-15 1.6
0

0101000
+114 35 -99 35 *
Wi

0101100
-112 37 -17 0 +36 37 +97 37 *
Fa
0  1e-07 36 36

0101000
+16 34 *
Wi

0101100
-110 0 +17 0 -103 0 +96 0 *
Fa
0  1e-07 37 0

0101000
+14 0 *
Ed
 1e-07 1 1 0
1  116 0 1.4194005804615e-16 1.6
0

0101000
+74 35 -89 35 *
Wi

0101100
-87 37 +12 0 -27 37 +72 37 *
Fa
0  1e-07 38 36

0101000
+11 34 *
Wi

0101100
-71 0 +12 0 -77 0 +85 0 *
Fa
0  1e-07 39 0

0101000
+9 0 *
Ed
 1e-07 1 1 0
1  117 0 4.73885543074869e-17 1.6
0

0101000
+46 35 -58 35 *
Wi

0101100
-43 0 +49 0 -7 0 +57 0 *
Fa
0  1e-07 40 0

0101000
+6 0 *
Wi

0101100
-44 37 +7 0 -33 37 -55 37 *
Fa
0  1e-07 41 36

0101000
+4 34 *
Sh

0101100
+278 12 -271 12 +264 12 +215 0 +166 0 +163 0 +160 12 -157 0 -150 0 -145 0 
-140 0 -130 12 +127 12 +118 12 +115 12 -105 12 +100 12 +92 12 -90 12 -80 12 
-75 12 +67 12 +65 12 -61 12 +52 12 -47 12 +40 12 -37 0 +34 12 +31 12 
-28 12 +25 12 -23 0 -20 41 +18 12 +15 12 +13 41 +10 12 -8 41 +5 41 
+3 12 *
So

0100000
+2 0 *

+1 1 ]]>
      </Part>
      <ElementMap new="1" count="1"><Element key="Dummy" value="Dummy"/></ElementMap>
      <ElementMap2 count="236">
<![CDATA[
1 PostfixCount 22
Edge
Face
Vertex
;:G3#dea;CUT;:H-13a9:c,E
;:G4#de2;CUT;:H-13a9:c,E
;:G5#ddf;CUT;:H-13a9:c,E
;:M;CUT;:H-13a9:7,F
;:G3#de9;CUT;:H-13a9:c,E
;:G4#de6;CUT;:H-13a9:c,E
;:G5#de3;CUT;:H-13a9:c,E
;:G#dec;CUT;:H-13a9:b,V
;:G2#deb;CUT;:H-13a9:c,V
;:M;CUT;:H-13a9:7,E
;:H1391,V
;:H1391,E
;:H1391,F
;:G#d23;CUT;:H1391:b,V
;:M;CUT;:H1391:7,E
;:M;CUT;:H1391:7,F
;:G#d22;CUT;:H1391:b,V
;:G#d2a;CUT;:H1391:b,V
;:G#d25;CUT;:H1391:b,V

MapCount 2

ElementMap 1 2 3

Edge

ChildCount 0

NameCount 118
0
$#c2d.f 0
$#c2e.f 0
$#c2f.f 0
$#c30.f 0
$#c31.f 0
$#c32.f 0
$#c33.f 0
$#c34.f 0
$#c35.f 0
$#c36.f 0
$#c41.f 0
$#db8.f 0
$#dbd.f 0
$#dbc.f 0
$#dbb.f 0
$#db5.f 0
$#dce.f 0
$#dcf.f 0
$#dd0.f 0
$#c51.f 0
$#dd1.f 0
$#c60.f 0
$#dd3.f 0
$#dd2.f 0
$#dd8.f 0
$#c4b.f 0
$#dd9.f 0
$#dda.f 0
$#dd4.f 0
$#dd5.f 0
$#c5c.f 0
$#dd6.f 0
$#c42.f 0
$#db9.f 0
$#ddd.12 0
$#ba1.6.79b.da4.daa.dde.ddf 0
$#de0.12 0
$#db6.f 0
$#dc2.f 0
$#dc3.f 0
$#dc5.f 0
$#dc4.f 0
$#dc6.f 0
$#dc7.f 0
$#dc9.f 0
$#dc8.f 0
$#dbe.f 0
$#dbf.f 0
$#dc1.f 0
$#dc0.f 0
$#dca.f 0
$#dcb.f 0
$#dcd.f 0
$#dcc.f 0
$#db7.f 0
$#c40.f 0
$#dba.f 0
$#ba1.5.d62.de1.de2 0
$#ba2.a.d62.de1.de3 0
$#de4.12 0
$#ba2.9.d61.de5.de6 0
$#de7.12 0
$#ba2.8.d60.de8.de9 0
$#ba1.4.d60.de8.dea 0
$#c73.f 0
$#c74.f 0
$#c75.f 0
$#c76.f 0
$#c77.f 0
$#c79.f 0
$#c7b.f 0
$#c7c.f 0
$#c7d.f 0
$#c7e.f 0
$#c82.f 0
$#cba.f 0
$#cbb.f 0
$#c8e.f 0
$#cbd.f 0
$#c8b.f 0
$#cc7.f 0
$#cc2.f 0
$#cbf.f 0
$#c85.f 0
$#c86.f 0
$#c89.f 0
$#c62.f 0
$#c63.f 0
$#c64.f 0
$#c65.f 0
$#c67.f 0
$#c6d.f 0
$#c72.f 0
$#c6a.f 0
$#c6b.f 0
$#c6c.f 0
$#c69.f 0
$#ca1.f 0
$#c98.f 0
$#cac.f 0
$#caa.f 0
$#ca9.f 0
$#c99.f 0
$#cb1.f 0
$#dd7.f 0
$#cae.f 0
$#caf.f 0
$#ca3.f 0
$#ba7.d 0
$#cc5.f 0
$#cb4.f 0
$#c81.f 0
$#c70.f 0
$#c83.f 0
$#cc6.f 0
$#c71.f 0
$#cb5.f 0

Face

ChildCount 0

NameCount 42
0
$#cc8.10 0
$#cc9.10 0
$#cca.10 0
$#ddc.10 0
$#dde.13.79b.da4.daa 0
$#ddb.10 0
$#cce.10 0
$#ccd.10 0
$#de1.13.d62 0
$#de5.13.d61 0
$#de8.13.d60 0
$#cd9.10 0
$#cda.10 0
$#cdb.10 0
$#cdd.10 0
$#ce2.10 0
$#cfb.10 0
$#ce0.10 0
$#ce1.10 0
$#cd2.10 0
$#cd8.10 0
$#cd4.10 0
$#cd3.10 0
$#ceb.10 0
$#ce7.10 0
$#cf4.10 0
$#ced.10 0
$#ba1.7 0
$#ce3.10 0
$#cec.10 0
$#cdc.10 0
$#cd5.10 0
$#ba2.7 0
$#cde.10 0
$#cdf.10 0
$#cf9.10 0
$#cfa.10 0
$#cd6.10 0
$#cd7.10 0
$#cf3.10 0
$#cf2.10 0

Vertex

ChildCount 0

NameCount 79
0
$#bb3.e $#bb4.e 0
$#bb5.e 0
$#bb6.e $#bb7.e 0
$#bb8.e 0
$#bb9.e $#bba.e 0
$#bbb.e 0
$#bbc.e $#bc3.e 0
$#bbe.e 0
$#bc7.e $#bab.e 0
$#dae.e 0
$#db2.e $#db3.e 0
$#db0.e $#db1.e 0
$#dac.e 0
$#bd2.e 0
$#bd3.e 0
$#bd4.e 0
$#bd5.e 0
$#bd6.e 0
$#be4.e 0
$#be5.e 0
$#bd9.e 0
$#bce.e 0
$#bcf.e 0
$#bd0.e 0
$#bd1.e 0
$#bda.e 0
$#bdb.e 0
$#be0.e 0
$#be1.e 0
$#bc9.e 0
$#daf.e 0
$#ddd.11.b9a.ba1.d23 0
$#de0.14.b9a.ba1.d22 0
$#dad.e 0
$#bff.e 0
$#c03.e 0
$#bfe.e 0
$#bfd.e 0
$#c0c.e 0
$#c07.e 0
$#c0d.e 0
$#c08.e 0
$#bf4.e 0
$#bf3.e 0
$#bf9.e 0
$#bf5.e 0
$#bea.e 0
$#be9.e 0
$#beb.e 0
$#bef.e 0
$#ba7.c.d62.de1.deb 0
$#de4.15.b9b.ba2.d2a 0
$#de7.16.b9b.ba2.d25 0
$#ba7.b.d60.de8.dec 0
$#bf0.e 0
$#bf1.e 0
$#bf2.e 0
$#bf6.e 0
$#bf7.e 0
$#bf8.e 0
$#c1a.e 0
$#c1b.e 0
$#c1c.e 0
$#c20.e 0
$#c1e.e 0
$#c1f.e 0
$#be6.e 0
$#be7.e 0
$#be8.e 0
$#bee.e 0
$#bec.e 0
$#bed.e 0
$#c12.e 0
$#c10.e 0
$#c11.e 0
$#c16.e 0
$#c14.e 0
$#c15.e 0

EndMap

ElementMap 2 1 3

Edge

ChildCount 1
1 0 117 5033 1 ;:H13a9,E 0

NameCount 0

Face

ChildCount 1
1 0 41 5033 1 ;:H13a9,F 0

NameCount 0

Vertex

ChildCount 1
1 0 78 5033 1 ;:H13a9,V 0

NameCount 0

EndMap
]]>
      </ElementMap2>
    </Property>
    <Property name="SingleSolid" type="App::PropertyBool">
      <Bool value="false"/>
    </Property>
    <Property name="Tip" type="App::PropertyLink">
      <Link value="Pad001"/>
    </Property>
    <Property name="TreeRank" type="App::PropertyInteger" status="2184">
      <Integer value="13"/>
    </Property>
    <Property name="ValidateShape" type="App::PropertyBool">
      <Bool value="false"/>
    </Property>
    <Property name="Visibility" type="App::PropertyBool" status="648">
      <Bool value="true"/>
    </Property>
    <Property name="_ExportChildren" type="App::PropertyLinkList" status="218104320">
      <LinkList count="5">
        <Link value="Boolean"/>
        <Link value="Sketch002"/>
        <Link value="Sketch001"/>
        <Link value="Pad"/>
        <Link value="Pad001"/>
      </LinkList>
    </Property>
    <Property name="_GroupVersion" type="App::PropertyInteger" status="218103808">
      <Integer value="1"/>
    </Property>
  </Properties>
</Object>
</Document>
