<?xml version='1.0' encoding='utf-8'?>
<!-- FreeCAD DocumentObject -->
<Document SchemaVersion="4" FileVersion="2">
<Object name="Boolean" Extensions="True">
  <Extensions Count="1">
    <Extension type="App::GeoFeatureGroupExtension" name="GeoFeatureGroupExtension">
    </Extension>
  </Extensions>
  <Properties Count="23" TransientCount="3">
    <_Property name="_Body" type="App::PropertyLinkHidden" status="251658240"/>
    <_Property name="_ElementMapVersion" type="App::PropertyString" status="234881024"/>
    <_Property name="_GroupTouched" type="App::PropertyBool" status="100663296"/>
    <Property name="BaseFeature" type="App::PropertyLink" status="8">
      <Link value="Cylinder"/>
    </Property>
    <Property name="ClaimAllChildren" type="App::PropertyBool" status="8">
      <Bool value="false"/>
    </Property>
    <Property name="ColoredElements" type="App::PropertyLinkSubHidden" status="218103808">
      <LinkSub value="" count="0">
      </LinkSub>
    </Property>
    <Property name="ExportMode" type="App::PropertyEnumeration" status="8">
      <Integer value="0"/>
    </Property>
    <Property name="ExpressionEngine" type="App::PropertyExpressionEngine" status="67108864">
      <ExpressionEngine count="0"></ExpressionEngine>
    </Property>
    <Property name="FixShape" type="App::PropertyEnumeration">
      <Integer value="1"/>
    </Property>
    <Property name="Group" type="App::PropertyLinkList">
      <LinkList count="2">
        <Link value="Reference"/>
        <Link value="Reference001"/>
      </LinkList>
    </Property>
    <Property name="InvalidShape" type="App::PropertyBool" status="67108864">
      <Bool value="false"/>
    </Property>
    <Property name="Label" type="App::PropertyString" status="134217728">
      <String value="Boolean"/>
    </Property>
    <Property name="Label2" type="App::PropertyString" status="128">
      <String value=""/>
    </Property>
    <Property name="NewSolid" type="App::PropertyBool">
      <Bool value="false"/>
    </Property>
    <Property name="Placement" type="App::PropertyPlacement" status="8388616">
      <PropertyPlacement Px="0" Py="0" Pz="0" Q0="0" Q1="0" Q2="0" Q3="1" A="0" Ox="0" Oy="0" Oz="1"/>
    </Property>
    <Property name="Refine" type="App::PropertyBool">
      <Bool value="true"/>
    </Property>
    <Property name="Shape" type="Part::PropertyPartShape">
      <Part HasherIndex="0" ElementMap="1.15.70200.4" brep="1">
<![CDATA[

CASCADE Topology V1, (c) Matra-Datavision
Locations 112
1
              1               0               0               0 
              0               1               0               0 
              0               0               1               0 
1
              1               0               0               0 
              0               1               0               0 
              0               0               1               0 
1
              1               0               0               0 
              0               1               0             -10 
              0               0               1               0 
1
              1               0               0               0 
              0               1               0               0 
              0               0               1               0 
1
              1               0               0               0 
              0               1               0             -10 
              0               0               1               0 
1
              1               0               0               0 
              0               1               0               0 
              0               0               1               0 
1
              1               0               0               0 
              0               1               0               0 
              0               0               1               0 
1
              1               0               0               0 
              0               1               0               0 
              0               0               1               0 
2  2 1 3 -1 4 1 5 1 6 1 7 1 8 1 0
1
              1               0               0               0 
              0               1               0               0 
              0               0               1               0 
1
              1               0               0               0 
              0               1               0               0 
              0               0               1               0 
2  10 1 11 1 0
1
              1               0               0              -0 
              0               1               0              -0 
              0               0               1            -3.7 
2  10 1 11 1 13 1 0
2  10 1 11 1 2 1 3 -1 4 1 5 1 6 1 7 1 8 1 0
2  8 -1 7 -1 6 -1 5 -1 4 -1 3 1 2 -1 11 -1 10 -1 0
2  10 1 11 1 13 1 2 1 3 -1 4 1 5 1 6 1 7 1 8 1 0
2  8 -1 7 -1 6 -1 5 -1 4 -1 3 1 2 -1 13 -1 11 -1 10 -1 0
1
              1               0               0               0 
              0               1               0               0 
              0               0               1               0 
1
              1               0               0              -0 
              0               1               0              -0 
              0               0               1              -0 
1
              1               0               0 1.59539048638635e-14 
              0               1               0            47.9 
              0               0               1 -1.59539048638635e-14 
1
              1               0               0               0 
              0               1               0               0 
              0               0               1               0 
1
              1               0               0               0 
              0               1               0               0 
              0               0               1               0 
1
              1               0               0               0 
              0               1               0               0 
              0               0               1               0 
1
              1               0               0               0 
              0               1               0               0 
              0               0               1               0 
1
             -1               0 1.22464679914735e-16              -5 
              0               1               0             -60 
-1.22464679914735e-16               0              -1           -1.85 
1
              1               0               0               0 
              0               1               0               0 
              0               0               1               0 
1
              1               0               0               0 
              0               1               0               0 
              0               0               1               0 
1
              1               0               0               0 
              0               1               0               0 
              0               0               1               0 
2  19 1 20 1 21 1 22 1 23 1 24 1 25 1 26 1 27 1 28 1 29 1 0
1
              1               0               0               0 
              0               1               0               0 
              0               0               1               0 
1
              1               0               0               0 
              0               1               0               0 
              0               0               1               0 
1
              1               0               0               0 
              0               1               0               0 
              0               0               1               0 
1
              1               0               0               0 
              0               1               0               0 
              0               0               1               0 
1
              1               0               0            2.05 
              0               1               0               0 
              0               0               1               0 
2  31 1 32 1 33 1 34 1 35 1 19 1 20 1 21 1 22 1 23 1 24 1 25 1 26 1 27 1 28 1 29 1 0
1
              1               0               0               0 
              0               1               0               0 
              0               0               1               0 
2  37 -1 21 -1 20 -1 19 -1 35 -1 34 -1 33 -1 32 -1 31 -1 0
1
              1               0               0               0 
              0               1               0               0 
              0               0               1               0 
1
              1               0               0               0 
              0 -4.44089209850063e-16              -1               0 
              0               1 -4.44089209850063e-16               0 
1
              1               0               0              -0 
              0               1               0             5.8 
              0               0               1 2.57571741713036e-15 
1
              1               0               0               0 
              0               1               0               0 
              0               0               1               0 
1
              1               0               0               0 
              0               1               0               0 
              0               0               1               0 
1
              1               0               0               0 
              0               1               0               0 
              0               0               1               0 
1
              1               0               0               0 
              0               1               0               0 
              0               0               1               0 
2  39 1 40 1 41 1 42 1 43 1 44 1 45 1 19 1 20 1 21 1 22 1 23 1 24 1 25 1 26 1 27 1 28 1 29 1 0
2  29 -1 28 -1 27 -1 26 -1 25 -1 24 -1 23 -1 22 -1 21 -1 20 -1 19 -1 45 -1 44 -1 43 -1 42 -1 41 -1 40 -1 39 -1 0
2  37 -1 21 -1 20 -1 19 -1 45 -1 44 -1 43 -1 42 -1 41 -1 40 -1 39 -1 0
2  41 -1 40 -1 39 -1 0
2  31 1 32 1 33 1 34 1 35 1 0
2  42 1 43 1 44 1 45 1 0
2  31 1 32 1 33 1 34 1 35 1 45 -1 44 -1 43 -1 42 -1 0
2  37 -1 21 -1 20 -1 19 -1 45 -1 44 -1 43 -1 42 -1 0
1
              1               0               0 1.19654286478976e-14 
              0               1               0          35.925 
              0               0               1 -1.19654286478976e-14 
2  19 1 20 1 54 1 22 1 23 1 24 1 25 1 26 1 27 1 28 1 29 1 0
2  39 1 40 1 42 1 43 1 44 1 45 1 19 1 20 1 21 1 22 1 23 1 24 1 25 1 26 1 27 1 28 1 29 1 0
2  37 -1 21 -1 20 -1 19 -1 45 -1 44 -1 43 -1 42 -1 40 -1 39 -1 0
2  29 -1 28 -1 27 -1 26 -1 25 -1 24 -1 23 -1 22 -1 21 -1 20 -1 19 -1 45 -1 44 -1 43 -1 42 -1 40 -1 39 -1 0
2  40 -1 39 -1 0
2  31 1 32 1 33 1 34 1 35 1 19 1 20 1 54 1 22 1 23 1 24 1 25 1 26 1 27 1 28 1 29 1 0
2  37 -1 54 -1 20 -1 19 -1 35 -1 34 -1 33 -1 32 -1 31 -1 0
2  39 1 40 1 41 1 42 1 43 1 44 1 45 1 19 1 20 1 54 1 22 1 23 1 24 1 25 1 26 1 27 1 28 1 29 1 0
2  29 -1 28 -1 27 -1 26 -1 25 -1 24 -1 23 -1 22 -1 54 -1 20 -1 19 -1 45 -1 44 -1 43 -1 42 -1 41 -1 40 -1 39 -1 0
2  37 -1 54 -1 20 -1 19 -1 45 -1 44 -1 43 -1 42 -1 41 -1 40 -1 39 -1 0
2  37 -1 54 -1 20 -1 19 -1 45 -1 44 -1 43 -1 42 -1 0
1
              1               0               0 7.97695243193175e-15 
              0               1               0           23.95 
              0               0               1 -7.97695243193175e-15 
2  19 1 20 1 66 1 22 1 23 1 24 1 25 1 26 1 27 1 28 1 29 1 0
2  39 1 40 1 42 1 43 1 44 1 45 1 19 1 20 1 54 1 22 1 23 1 24 1 25 1 26 1 27 1 28 1 29 1 0
2  37 -1 54 -1 20 -1 19 -1 45 -1 44 -1 43 -1 42 -1 40 -1 39 -1 0
2  29 -1 28 -1 27 -1 26 -1 25 -1 24 -1 23 -1 22 -1 54 -1 20 -1 19 -1 45 -1 44 -1 43 -1 42 -1 40 -1 39 -1 0
2  31 1 32 1 33 1 34 1 35 1 19 1 20 1 66 1 22 1 23 1 24 1 25 1 26 1 27 1 28 1 29 1 0
2  37 -1 66 -1 20 -1 19 -1 35 -1 34 -1 33 -1 32 -1 31 -1 0
2  39 1 40 1 41 1 42 1 43 1 44 1 45 1 19 1 20 1 66 1 22 1 23 1 24 1 25 1 26 1 27 1 28 1 29 1 0
2  29 -1 28 -1 27 -1 26 -1 25 -1 24 -1 23 -1 22 -1 66 -1 20 -1 19 -1 45 -1 44 -1 43 -1 42 -1 41 -1 40 -1 39 -1 0
2  37 -1 66 -1 20 -1 19 -1 45 -1 44 -1 43 -1 42 -1 41 -1 40 -1 39 -1 0
2  37 -1 66 -1 20 -1 19 -1 45 -1 44 -1 43 -1 42 -1 0
1
              1               0               0               0 
              0               1               0               0 
              0               0               1               0 
2  77 1 22 1 23 1 24 1 25 1 26 1 27 1 28 1 29 1 0
2  37 -1 77 -1 35 -1 34 -1 33 -1 32 -1 31 -1 0
2  37 -1 77 -1 45 -1 44 -1 43 -1 42 -1 0
2  31 1 32 1 33 1 34 1 35 1 77 1 22 1 23 1 24 1 25 1 26 1 27 1 28 1 29 1 0
2  39 1 40 1 41 1 42 1 43 1 44 1 45 1 77 1 22 1 23 1 24 1 25 1 26 1 27 1 28 1 29 1 0
2  29 -1 28 -1 27 -1 26 -1 25 -1 24 -1 23 -1 22 -1 77 -1 45 -1 44 -1 43 -1 42 -1 41 -1 40 -1 39 -1 0
2  37 -1 77 -1 45 -1 44 -1 43 -1 42 -1 41 -1 40 -1 39 -1 0
1
              1               0               0 3.98847621596587e-15 
              0               1               0          11.975 
              0               0               1 -3.98847621596587e-15 
2  19 1 20 1 85 1 22 1 23 1 24 1 25 1 26 1 27 1 28 1 29 1 0
2  42 1 43 1 44 1 45 1 77 1 22 1 23 1 24 1 25 1 26 1 27 1 28 1 29 1 0
2  39 1 40 1 0
2  37 -1 77 -1 45 -1 44 -1 43 -1 42 -1 40 -1 39 -1 0
2  39 1 40 1 41 1 0
2  39 1 40 1 42 1 43 1 44 1 45 1 19 1 20 1 85 1 22 1 23 1 24 1 25 1 26 1 27 1 28 1 29 1 0
2  37 -1 85 -1 20 -1 19 -1 45 -1 44 -1 43 -1 42 -1 40 -1 39 -1 0
2  29 -1 28 -1 27 -1 26 -1 25 -1 24 -1 23 -1 22 -1 85 -1 20 -1 19 -1 45 -1 44 -1 43 -1 42 -1 40 -1 39 -1 0
2  31 1 32 1 33 1 34 1 35 1 19 1 20 1 85 1 22 1 23 1 24 1 25 1 26 1 27 1 28 1 29 1 0
2  37 -1 85 -1 20 -1 19 -1 35 -1 34 -1 33 -1 32 -1 31 -1 0
2  37 -1 85 -1 20 -1 19 -1 45 -1 44 -1 43 -1 42 -1 0
2  42 1 43 1 44 1 45 1 19 1 20 1 85 1 22 1 23 1 24 1 25 1 26 1 27 1 28 1 29 1 0
2  37 -1 85 -1 20 -1 19 -1 45 -1 44 -1 43 -1 42 -1 41 -1 40 -1 39 -1 0
2  39 1 40 1 41 1 42 1 43 1 44 1 45 1 19 1 20 1 85 1 22 1 23 1 24 1 25 1 26 1 27 1 28 1 29 1 0
2  29 -1 28 -1 27 -1 26 -1 25 -1 24 -1 23 -1 22 -1 85 -1 20 -1 19 -1 45 -1 44 -1 43 -1 42 -1 41 -1 40 -1 39 -1 0
2  39 1 40 1 42 1 43 1 44 1 45 1 19 1 20 1 66 1 22 1 23 1 24 1 25 1 26 1 27 1 28 1 29 1 0
2  37 -1 66 -1 20 -1 19 -1 45 -1 44 -1 43 -1 42 -1 40 -1 39 -1 0
2  29 -1 28 -1 27 -1 26 -1 25 -1 24 -1 23 -1 22 -1 66 -1 20 -1 19 -1 45 -1 44 -1 43 -1 42 -1 40 -1 39 -1 0
2  42 1 43 1 44 1 45 1 19 1 20 1 66 1 22 1 23 1 24 1 25 1 26 1 27 1 28 1 29 1 0
2  42 1 43 1 44 1 45 1 19 1 20 1 54 1 22 1 23 1 24 1 25 1 26 1 27 1 28 1 29 1 0
2  42 1 43 1 44 1 45 1 19 1 20 1 21 1 22 1 23 1 24 1 25 1 26 1 27 1 28 1 29 1 0
2  37 -1 22 1 23 1 24 1 25 1 26 1 27 1 28 1 29 1 0
2  4 1 5 1 6 1 7 1 8 1 0
1
              1               0               0               0 
              0               1               0               0 
              0               0               1               2 
2  109 -1 0
2  109 1 4 1 5 1 6 1 7 1 8 1 0
2  39 1 40 1 42 1 43 1 44 1 45 1 77 1 22 1 23 1 24 1 25 1 26 1 27 1 28 1 29 1 0
Curve2ds 33
8 -0.92500000000000338 2.7749999999999835
1 -0.92499999999998328 -1.1509949194771976 1 1.22464679914735e-16 
8 -0.92500000000000338 2.7749999999999835
1 53.699999999999996 -0.92500000000000338 -3.7126059029894287e-16 -1 
1 0 -5.7999999999999998 1 0 
1 0 -5.7999999999999998 1 0 
1 0 -5.7999999999999998 1 0 
1 3.1415926535897931 -8.2156503822261608e-16 0 -1 
1 0 -1.01965261644937e-45 1 2.1786150163164135e-46 
1 0 4.2209728544990556e-46 1 -8.8087329821058537e-47 
1 6.2831853071795862 0 0 1 
8 -2.7749999999999835 0.92500000000000071
1 0.92499999999998417 -1.1509949194771993 1 -1.22464679914735e-16 
8 -2.7749999999999835 0.92500000000000071
1 47.899999999999999 -0.92500000000000071 3.4341604602652235e-16 1 
8 -0.92500000000000315 2.7749999999999879
1 -0.9249999999999875 -1.1509949194771931 1 1.22464679914735e-16 
8 -0.92500000000000315 2.7749999999999879
1 41.724999999999994 -0.92500000000000315 -3.7126059029894287e-16 -1 
1 0 0 1 0 
8 -2.7749999999999875 0.92500000000000071
1 0.92499999999998817 -1.150994919477194 1 -1.22464679914735e-16 
8 -2.7749999999999875 0.92500000000000071
1 35.924999999999997 -0.92500000000000071 3.4341604602652235e-16 1 
8 -0.92500000000000293 2.7749999999999919
1 -0.92499999999999172 -1.1509949194771896 1 1.22464679914735e-16 
8 -0.92500000000000293 2.7749999999999919
1 29.75 -0.92500000000000293 -3.7126059029894287e-16 -1 
8 -0.92500000000000238 2.7749999999999977
1 -0.92500000000000016 -1.1509949194771816 1 1.22464679914735e-16 
8 -0.92500000000000238 2.7749999999999977
1 5.7999999999999972 -0.92500000000000249 -3.7126059029894287e-16 -1 
8 -2.7749999999999959 0.9250000000000006
1 0.92499999999999627 -1.1509949194771869 1 -1.22464679914735e-16 
8 -2.7749999999999959 0.9250000000000006
1 11.975000000000001 -0.9250000000000006 3.4341604602652235e-16 1 
1 0 0 0 -1 
1 6.2831853071795862 0 0 -1 
8 -0.92500000000000271 2.7749999999999964
1 -0.92499999999999594 -1.1509949194771851 1 1.22464679914735e-16 
8 -0.92500000000000271 2.7749999999999964
1 17.774999999999999 -0.92500000000000271 -3.7126059029894287e-16 -1 
8 -2.7749999999999915 0.9250000000000006
1 0.92499999999999227 -1.1509949194771905 1 -1.22464679914735e-16 
8 -2.7749999999999915 0.9250000000000006
1 23.950000000000003 -0.9250000000000006 3.4341604602652235e-16 1 
2 0 0 1 0 -0 1 1.8500000000000001
1 0 0 1 0 
1 0 -2 1 0 
1 0 0 0 -1 
1 6.2831853071795862 0 0 -1 
Curves 82
1 -5 0 0 -0 -0 -1 
1 5 0 0 -0 -0 -1 
1 -5 0 0 1 0 0 
1 5 -60 0 -0 -0 -1 
1 5 0 0 0 -1 0 
1 -5 -60 0 0 1 0 
1 -5 -6.3000000000000034 -0.92500000000000338 0 -3.7126059029894287e-16 -1 
2 -2.5757174171303631e-15 5.7999999999999998 -5.7192415628523354e-31 4.4408920985006262e-16 -1 9.8607613152626476e-32 -2.2204460492503131e-16 0 1 -1 -4.4408920985006262e-16 -2.2204460492503131e-16 1.8500000000000001
2 -2.5757174171303631e-15 5.7999999999999998 -5.7192415628523354e-31 4.4408920985006262e-16 -1 9.8607613152626476e-32 -2.2204460492503131e-16 0 1 -1 -4.4408920985006262e-16 -2.2204460492503131e-16 1.8500000000000001
1 -1 1.8500000000000001 0 1 0 0 
1 2.0499999999999998 -1.8500000000000001 0 -1 0 0 
2 2.0499999999999998 5.4027101302882546e-17 0 0 0 1 1 0 -0 -0 1 0 1.05
1 2.0499999999999998 8.2156503822261588e-16 -1.8500000000000001 0 1 4.4408920985006262e-16 
2 0 0 0 4.4408920985006262e-16 -1 9.8607613152626476e-32 -2.2204460492503131e-16 0 1 -1 -4.4408920985006262e-16 -2.2204460492503131e-16 1.8500000000000001
2 0 0 0 4.4408920985006262e-16 -1 9.8607613152626476e-32 -2.2204460492503131e-16 0 1 -1 -4.4408920985006262e-16 -2.2204460492503131e-16 1.8500000000000001
7 0 0  1 2 2  -2.9864999362416705e-15 5.7999999999999989 1.8500000000000001  -4.1078251911130794e-16 0 1.8500000000000001 
 -5.7999999999999989 2 0 2
1 -5 -12.100000000000001 -0.92500000000000071 -0 3.4341604602652235e-16 1 
1 -5 -18.275000000000006 -0.92500000000000315 0 -3.7126059029894287e-16 -1 
1 2.0499999999999998 -1.8500000000000001 0 -1 0 0 
1 -1 1.8500000000000001 0 1 0 0 
2 2.0499999999999998 5.4027101302882546e-17 0 0 0 1 1 0 -0 -0 1 0 1.05
2 -2.5757174171303631e-15 5.7999999999999998 -5.7192415628523354e-31 4.4408920985006262e-16 -1 9.8607613152626476e-32 -2.2204460492503131e-16 0 1 -1 -4.4408920985006262e-16 -2.2204460492503131e-16 1.8500000000000001
2 -2.5757174171303631e-15 5.7999999999999998 -5.7192415628523354e-31 4.4408920985006262e-16 -1 9.8607613152626476e-32 -2.2204460492503131e-16 0 1 -1 -4.4408920985006262e-16 -2.2204460492503131e-16 1.8500000000000001
1 -1 1.8500000000000001 0 1 0 0 
1 2.0499999999999998 -1.8500000000000001 0 -1 0 0 
2 2.0499999999999998 5.4027101302882546e-17 0 0 0 1 1 0 -0 -0 1 0 1.05
1 2.0499999999999998 8.2156503822261588e-16 -1.8500000000000001 0 1 4.4408920985006262e-16 
2 0 0 0 4.4408920985006262e-16 -1 9.8607613152626476e-32 -2.2204460492503131e-16 0 1 -1 -4.4408920985006262e-16 -2.2204460492503131e-16 1.8500000000000001
2 0 0 0 4.4408920985006262e-16 -1 9.8607613152626476e-32 -2.2204460492503131e-16 0 1 -1 -4.4408920985006262e-16 -2.2204460492503131e-16 1.8500000000000001
7 0 0  1 2 2  -2.9864999362416705e-15 5.7999999999999989 1.8500000000000001  -4.1078251911130794e-16 0 1.8500000000000001 
 -5.7999999999999989 2 0 2
1 -5 -24.075000000000003 -0.92500000000000071 -0 3.4341604602652235e-16 1 
1 -5 -30.25 -0.92500000000000293 0 -3.7126059029894287e-16 -1 
1 2.0499999999999998 -1.8500000000000001 0 -1 0 0 
1 -1 1.8500000000000001 0 1 0 0 
2 2.0499999999999998 5.4027101302882546e-17 0 0 0 1 1 0 -0 -0 1 0 1.05
2 -2.5757174171303631e-15 5.7999999999999998 -5.7192415628523354e-31 4.4408920985006262e-16 -1 9.8607613152626476e-32 -2.2204460492503131e-16 0 1 -1 -4.4408920985006262e-16 -2.2204460492503131e-16 1.8500000000000001
2 -2.5757174171303631e-15 5.7999999999999998 -5.7192415628523354e-31 4.4408920985006262e-16 -1 9.8607613152626476e-32 -2.2204460492503131e-16 0 1 -1 -4.4408920985006262e-16 -2.2204460492503131e-16 1.8500000000000001
1 -1 1.8500000000000001 0 1 0 0 
1 2.0499999999999998 -1.8500000000000001 0 -1 0 0 
2 2.0499999999999998 5.4027101302882546e-17 0 0 0 1 1 0 -0 -0 1 0 1.05
1 2.0499999999999998 8.2156503822261588e-16 -1.8500000000000001 0 1 4.4408920985006262e-16 
2 0 0 0 4.4408920985006262e-16 -1 9.8607613152626476e-32 -2.2204460492503131e-16 0 1 -1 -4.4408920985006262e-16 -2.2204460492503131e-16 1.8500000000000001
2 0 0 0 4.4408920985006262e-16 -1 9.8607613152626476e-32 -2.2204460492503131e-16 0 1 -1 -4.4408920985006262e-16 -2.2204460492503131e-16 1.8500000000000001
7 0 0  1 2 2  -2.9864999362416705e-15 5.7999999999999989 1.8500000000000001  -4.1078251911130794e-16 0 1.8500000000000001 
 -5.7999999999999989 2 0 2
2 -2.5757174171303631e-15 5.7999999999999998 -5.7192415628523354e-31 4.4408920985006262e-16 -1 9.8607613152626476e-32 -2.2204460492503131e-16 0 1 -1 -4.4408920985006262e-16 -2.2204460492503131e-16 1.8500000000000001
2 -2.5757174171303631e-15 5.7999999999999998 -5.7192415628523354e-31 4.4408920985006262e-16 -1 9.8607613152626476e-32 -2.2204460492503131e-16 0 1 -1 -4.4408920985006262e-16 -2.2204460492503131e-16 1.8500000000000001
1 2.0499999999999998 8.2156503822261588e-16 -1.8500000000000001 0 1 4.4408920985006262e-16 
2 0 0 0 4.4408920985006262e-16 -1 9.8607613152626476e-32 -2.2204460492503131e-16 0 1 -1 -4.4408920985006262e-16 -2.2204460492503131e-16 1.8500000000000001
2 0 0 0 4.4408920985006262e-16 -1 9.8607613152626476e-32 -2.2204460492503131e-16 0 1 -1 -4.4408920985006262e-16 -2.2204460492503131e-16 1.8500000000000001
7 0 0  1 2 2  -2.9864999362416705e-15 5.7999999999999989 1.8500000000000001  -4.1078251911130794e-16 0 1.8500000000000001 
 -5.7999999999999989 2 0 2
1 -1 1.8500000000000001 0 1 0 0 
1 -5 -54.200000000000003 -0.92500000000000249 0 -3.7126059029894287e-16 -1 
1 2.0499999999999998 -1.8500000000000001 0 -1 0 0 
2 2.0499999999999998 5.4027101302882546e-17 0 0 0 1 1 0 -0 -0 1 0 1.05
1 -5 -48.024999999999999 -0.9250000000000006 -0 3.4341604602652235e-16 1 
1 3.0999999999999996 -2.3992852728086398e-32 5.4027101302882546e-17 0 1 4.4408920985006262e-16 
2 2.0499999999999998 5.4027101302882546e-17 0 0 0 1 1 0 -0 -0 1 0 1.05
1 2.0499999999999998 -1.8500000000000001 0 -1 0 0 
1 -1 1.8500000000000001 0 1 0 0 
2 0 0 0 4.4408920985006262e-16 -1 9.8607613152626476e-32 -2.2204460492503131e-16 0 1 -1 -4.4408920985006262e-16 -2.2204460492503131e-16 1.8500000000000001
2 0 0 0 4.4408920985006262e-16 -1 9.8607613152626476e-32 -2.2204460492503131e-16 0 1 -1 -4.4408920985006262e-16 -2.2204460492503131e-16 1.8500000000000001
2 2.0499999999999998 5.4027101302882546e-17 0 0 0 1 1 0 -0 -0 1 0 1.05
2 -2.5757174171303631e-15 5.7999999999999998 -5.7192415628523354e-31 4.4408920985006262e-16 -1 9.8607613152626476e-32 -2.2204460492503131e-16 0 1 -1 -4.4408920985006262e-16 -2.2204460492503131e-16 1.8500000000000001
2 -2.5757174171303631e-15 5.7999999999999998 -5.7192415628523354e-31 4.4408920985006262e-16 -1 9.8607613152626476e-32 -2.2204460492503131e-16 0 1 -1 -4.4408920985006262e-16 -2.2204460492503131e-16 1.8500000000000001
1 2.0499999999999998 8.2156503822261588e-16 -1.8500000000000001 0 1 4.4408920985006262e-16 
7 0 0  1 2 2  -2.9864999362416705e-15 5.7999999999999989 1.8500000000000001  -4.1078251911130794e-16 0 1.8500000000000001 
 -5.7999999999999989 2 0 2
1 3.0999999999999996 -2.3992852728086398e-32 5.4027101302882546e-17 0 1 4.4408920985006262e-16 
2 2.0499999999999998 5.4027101302882546e-17 0 0 0 1 1 0 -0 -0 1 0 1.05
1 -1 1.8500000000000001 0 1 0 0 
1 -5 -42.225000000000001 -0.92500000000000271 0 -3.7126059029894287e-16 -1 
1 2.0499999999999998 -1.8500000000000001 0 -1 0 0 
1 -5 -36.049999999999997 -0.9250000000000006 -0 3.4341604602652235e-16 1 
1 2.0499999999999998 -1.8500000000000001 0 -1 0 0 
1 -1 1.8500000000000001 0 1 0 0 
2 2.0499999999999998 5.4027101302882546e-17 0 0 0 1 1 0 -0 -0 1 0 1.05
1 3.0999999999999996 -2.3992852728086398e-32 5.4027101302882546e-17 0 1 4.4408920985006262e-16 
1 3.0999999999999996 -2.3992852728086398e-32 5.4027101302882546e-17 0 1 4.4408920985006262e-16 
1 3.0999999999999996 -2.3992852728086398e-32 5.4027101302882546e-17 0 1 4.4408920985006262e-16 
1 -7.0500000000000007 -60 -2.2204460492503131e-16 1 -0 1.22464679914735e-16 
2 0 0 0 0 0 1 1 0 -0 -0 1 0 1.8500000000000001
1 1.8500000000000001 -4.5311931568452072e-16 0 0 0 1 
1 -4 -60 -3.7000000000000002 -1 0 -1.22464679914735e-16 
Polygon3D 0
PolygonOnTriangulations 0
Surfaces 27
1 -5 0 0 0 -1 0 1 0 0 -0 0 1 
1 5 0 0 -1 0 0 0 -1 0 0 0 1 
1 -5 -60 0 1 0 0 -0 1 0 0 -0 1 
1 1.1509949194771816 5.7999999999999989 2.4924305231022334e-15 0 1 3.7126059029894287e-16 0 -3.7126059029894287e-16 1 1 0 -0 
10 0 6.2831853071795862 -5.8000000000000007 8.8817841970012523e-16
2 0 0 0 4.4408920985006262e-16 -1 9.8607613152626476e-32 -2.2204460492503131e-16 0 1 -1 -4.4408920985006262e-16 -2.2204460492503131e-16 1.8500000000000001
2 2.0499999999999998 -2.3992852728086398e-32 5.4027101302882546e-17 0 -1 -4.4408920985006262e-16 1 0 0 0 -4.4408920985006262e-16 1 1.05
1 1.1509949194771827 1.8887516470524373e-16 6.8559693472153121e-16 -0 -1 -3.4341604602652235e-16 0 3.4341604602652235e-16 -1 1 -0 0 
1 1.1509949194771816 5.7999999999999989 2.4924305231022334e-15 0 1 3.7126059029894287e-16 0 -3.7126059029894287e-16 1 1 0 -0 
10 0 6.2831853071795862 -5.8000000000000007 8.8817841970012523e-16
2 0 0 0 4.4408920985006262e-16 -1 9.8607613152626476e-32 -2.2204460492503131e-16 0 1 -1 -4.4408920985006262e-16 -2.2204460492503131e-16 1.8500000000000001
2 2.0499999999999998 -2.3992852728086398e-32 5.4027101302882546e-17 0 -1 -4.4408920985006262e-16 1 0 0 0 -4.4408920985006262e-16 1 1.05
1 1.1509949194771827 1.8887516470524373e-16 6.8559693472153121e-16 -0 -1 -3.4341604602652235e-16 0 3.4341604602652235e-16 -1 1 -0 0 
1 1.1509949194771816 5.7999999999999989 2.4924305231022334e-15 0 1 3.7126059029894287e-16 0 -3.7126059029894287e-16 1 1 0 -0 
10 0 6.2831853071795862 -5.8000000000000007 8.8817841970012523e-16
2 0 0 0 4.4408920985006262e-16 -1 9.8607613152626476e-32 -2.2204460492503131e-16 0 1 -1 -4.4408920985006262e-16 -2.2204460492503131e-16 1.8500000000000001
2 2.0499999999999998 -2.3992852728086398e-32 5.4027101302882546e-17 0 -1 -4.4408920985006262e-16 1 0 0 0 -4.4408920985006262e-16 1 1.05
10 0 6.2831853071795862 -5.8000000000000007 8.8817841970012523e-16
2 0 0 0 4.4408920985006262e-16 -1 9.8607613152626476e-32 -2.2204460492503131e-16 0 1 -1 -4.4408920985006262e-16 -2.2204460492503131e-16 1.8500000000000001
1 1.1509949194771816 5.7999999999999989 2.4924305231022334e-15 0 1 3.7126059029894287e-16 0 -3.7126059029894287e-16 1 1 0 -0 
2 2.0499999999999998 -2.3992852728086398e-32 5.4027101302882546e-17 0 -1 -4.4408920985006262e-16 1 0 0 0 -4.4408920985006262e-16 1 1.05
1 1.1509949194771827 1.8887516470524373e-16 6.8559693472153121e-16 -0 -1 -3.4341604602652235e-16 0 3.4341604602652235e-16 -1 1 -0 0 
10 0 6.2831853071795862 -5.8000000000000007 8.8817841970012523e-16
2 0 0 0 4.4408920985006262e-16 -1 9.8607613152626476e-32 -2.2204460492503131e-16 0 1 -1 -4.4408920985006262e-16 -2.2204460492503131e-16 1.8500000000000001
2 2.0499999999999998 -2.3992852728086398e-32 5.4027101302882546e-17 0 -1 -4.4408920985006262e-16 1 0 0 0 -4.4408920985006262e-16 1 1.05
1 1.1509949194771816 5.7999999999999989 2.4924305231022334e-15 0 1 3.7126059029894287e-16 0 -3.7126059029894287e-16 1 1 0 -0 
1 1.1509949194771827 1.8887516470524373e-16 6.8559693472153121e-16 -0 -1 -3.4341604602652235e-16 0 3.4341604602652235e-16 -1 1 -0 0 
1 -1.1399532710280411 -30.40233644859811 2.0008224914194834e-15 3.759406001451288e-16 0 1 1 0 -3.759406001451288e-16 -0 1 0 
1 0 0 0 0 0 1 1 0 -0 -0 1 0 
2 0 0 0 -0 -0 -1 1 0 -0 -0 1 0 1.8500000000000001
1 -1.5895300862651529 -60 -1.8500000000000003 -0 -1 -0 0 0 -1 1 -0 0 
1 -1.1399532710280407 -30.402336448598113 -3.6999999999999984 -4.2637470783942767e-16 -0 -1 -1 0 4.2637470783942767e-16 0 1 -0 
Triangulations 0

TShapes 230
Ve
1.00000000030201e-05
-5 0 0
0 0

0101101
*
Ed
 1e-07 1 1 0
1  1 0 0 3.7
0

0101000
+230 12 -230 14 *
Ve
1.00000000030201e-05
5 0 0
0 0

0101101
*
Ed
 1e-07 1 1 0
1  2 0 0 3.7
0

0101000
+228 12 -228 14 *
Ed
 1.00000000030201e-05 1 1 0
1  3 0 0 10
0

0101000
+230 0 -228 0 *
Wi

0101100
+229 0 -227 0 -226 12 +226 14 *
Fa
0  1e-07 1 0

0111000
+225 0 *
Ve
1.00000000030201e-05
5 -60 0
0 0

0101101
*
Ed
 1.00000000030201e-05 1 1 0
1  4 0 0 3.7
0

0101000
+223 12 -223 14 *
Ed
 1.00000000030201e-05 1 1 0
1  5 0 0 60
0

0101000
+228 0 -223 0 *
Wi

0101100
+227 0 -222 0 -221 12 +221 14 *
Fa
0  1e-07 2 0

0111000
+220 0 *
Ve
1.00000000030201e-05
-5 -6.3 6.67584214220103e-15
0 0

0101101
*
Ed
 1.00000000030201e-05 1 1 0
1  6 0 53.7 60
0

0101000
+218 16 -230 0 *
Ve
1.00000000030201e-05
-5 -6.3 -3.69999999999999
0 0

0101101
*
Ed
 1.00000000030201e-05 1 1 0
1  6 0 53.7 60
0

0101000
+216 18 -230 0 *
Ed
 1.50000014528149e-07 1 1 0
1  7 0 -0.925000000000003 2.77499999999998
2  1 4 30 -0.925000000000003 2.77499999999998
2  2 3 9 -0.925000000000003 2.77499999999998
0

0101000
+218 0 -216 0 *
Wi

0101100
-217 15 -229 9 +215 17 +214 0 *
Fa
0  1e-07 3 9

0101000
+213 0 *
Ve
1.00000000045097e-05
2.05000000000002 53.7 -1.85000000000002
0 0

0101101
*
Ve
1.00000015523806e-07
3.90000000000002 53.7 -1.51130784723291e-14
0 0

0101101
*
Ed
 1.00000014528149e-07 1 1 0
1  8 0 3.14159265358979 4.71238898038469
2  3 5 0 3.14159265358979 4.71238898038469
0

0101000
+211 38 -210 38 *
Ve
1.00000000030201e-05
2.05000000000001 53.7 1.84999999999999
0 0

0101101
*
Ed
 1.00000014528149e-07 1 1 0
1  9 0 4.71238898038469 6.28318530717959
2  4 5 0 4.71238898038469 6.28318530717959
0

0101000
+210 38 -208 38 *
Ed
 1.00000000030201e-05 1 1 0
1  10 0 0.999999999999984 3.05
0

0101000
+216 47 -208 48 *
Ed
 1.00000000030201e-05 1 1 0
1  11 0 0 2.05000000000002
0

0101000
+211 48 -218 47 *
Wi

0101100
-209 36 -207 36 +206 46 +214 0 +205 46 *
Ve
1e-07
3.10000000000002 53.7 -1.33241603454302e-14
0 0

0101101
*
Ed
 1e-07 1 1 0
1  12 0 0 6.28318530717959
2  5 6 49 0 6.28318530717959
0

0101100
+203 48 -203 48 *
Wi

0101100
+202 46 *
Fa
0  1.00000014528149e-07 4 30

0101000
+204 0 +201 0 *
Ve
1.00000000034309e-05
2.05000000000002 47.9 -1.85000000000002
0 0

0101101
*
Ed
 1.00000000030201e-05 1 1 0
1  13 0 0 5.8
2  6 5 52 0 5.8
0

0101000
+199 53 -211 53 *
Ve
1.00000014528149e-07
3.90000000000002 47.9 -1.63550184491013e-14
0 0

0101101
*
Ed
 1.00000014528149e-07 1 1 0
1  14 0 3.14159265358979 4.71238898038469
2  7 5 0 3.14159265358979 4.71238898038469
0

0101000
+199 38 -197 38 *
Ve
1.00000000030201e-05
2.05000000000002 47.9 1.84999999999998
0 0

0101101
*
Ed
 1.00000014528149e-07 1 1 0
1  15 0 4.71238898038469 6.28318530717959
2  8 5 0 4.71238898038469 6.28318530717959
0

0101000
+197 38 -195 38 *
Ed
 1.00000000030201e-05 1 1 0
1  16 0 -5.8 0
2  9 5 0 -5.8 0
0

0101000
+208 38 -195 38 *
Wi

0101100
+207 50 +209 50 +198 51 -196 50 -194 50 +193 50 *
Fa
0  1e-07 5 50

0111000
+192 0 *
Ve
1.00000000030201e-05
-5 -18.275 4.67744069787575e-15
0 0

0101101
*
Ve
1.00000000030201e-05
-5 -12.1 8.00810977175122e-15
0 0

0101101
*
Ed
 1.00000000030201e-05 1 1 0
1  6 0 41.725 47.9
0

0101000
+190 16 -189 16 *
Ve
1.00000000030201e-05
-5 -12.1 -3.69999999999999
0 0

0101101
*
Ed
 1.50000014528149e-07 1 1 0
1  17 0 -2.77499999999998 0.925000000000001
2  10 7 30 -2.77499999999998 0.925000000000001
2  11 3 9 -2.77499999999998 0.925000000000001
0

0101000
+187 0 -189 0 *
Ve
1.00000000030201e-05
-5 -18.275 -3.7
0 0

0101101
*
Ed
 1.00000000030201e-05 1 1 0
1  6 0 41.725 47.9
0

0101000
+185 18 -187 18 *
Ed
 1.50000014528149e-07 1 1 0
1  18 0 -0.925000000000003 2.77499999999999
2  12 8 55 -0.925000000000003 2.77499999999999
2  13 3 9 -0.925000000000003 2.77499999999999
0

0101000
+190 0 -185 0 *
Wi

0101100
-188 15 +186 0 +184 17 +183 0 *
Fa
0  1e-07 3 9

0101000
+182 0 *
Ed
 1.00000000030201e-05 1 1 0
1  19 0 0 2.05000000000002
0

0101000
+199 57 -189 58 *
Ed
 1.00000000030201e-05 1 1 0
1  20 0 0.999999999999984 3.05
0

0101000
+187 58 -195 57 *
Wi

0101100
-180 56 +186 0 -179 56 +194 36 +196 36 *
Ve
1e-07
3.10000000000002 47.9 -1.58998777625606e-14
0 0

0101101
*
Ed
 1e-07 1 1 0
1  21 0 0 6.28318530717959
2  14 6 59 0 6.28318530717959
0

0101100
+177 57 -177 57 *
Wi

0101100
-176 56 *
Fa
0  1.00000014528149e-07 7 30

0101000
+178 0 +175 0 *
Ve
1.00000000045097e-05
2.05000000000001 41.725 -1.85000000000001
0 0

0101101
*
Ve
1.00000015523806e-07
3.90000000000001 41.725 -1.11246022563632e-14
0 0

0101101
*
Ed
 1.00000014528149e-07 1 1 0
1  22 0 3.14159265358979 4.71238898038469
2  3 9 0 3.14159265358979 4.71238898038469
0

0101000
+173 61 -172 61 *
Ve
1.00000000030201e-05
2.05000000000001 41.725 1.84999999999999
0 0

0101101
*
Ed
 1.00000014528149e-07 1 1 0
1  23 0 4.71238898038469 6.28318530717959
2  4 9 0 4.71238898038469 6.28318530717959
0

0101000
+172 61 -170 61 *
Ed
 1.00000000030201e-05 1 1 0
1  24 0 0.999999999999988 3.05
0

0101000
+185 63 -170 64 *
Ed
 1.00000000030201e-05 1 1 0
1  25 0 0 2.05000000000001
0

0101000
+173 64 -190 63 *
Wi

0101100
-171 60 -169 60 +168 62 +183 0 +167 62 *
Ve
1e-07
3.10000000000001 41.725 -9.33568412946437e-15
0 0

0101101
*
Ed
 1e-07 1 1 0
1  26 0 0 6.28318530717959
2  5 10 49 0 6.28318530717959
0

0101100
+165 64 -165 64 *
Wi

0101100
+164 62 *
Fa
0  1.00000014528149e-07 8 55

0101000
+166 0 +163 0 *
Ve
1.00000000034309e-05
2.05000000000001 35.925 -1.85000000000001
0 0

0101101
*
Ed
 1.00000000030201e-05 1 1 0
1  27 0 0 5.8
2  6 9 52 0 5.8
0

0101000
+161 65 -173 65 *
Ve
1.00000014528149e-07
3.90000000000001 35.925 -1.23665422331354e-14
0 0

0101101
*
Ed
 1.00000014528149e-07 1 1 0
1  28 0 3.14159265358979 4.71238898038469
2  7 9 0 3.14159265358979 4.71238898038469
0

0101000
+161 61 -159 61 *
Ve
1.00000000030201e-05
2.05000000000001 35.925 1.84999999999999
0 0

0101101
*
Ed
 1.00000014528149e-07 1 1 0
1  29 0 4.71238898038469 6.28318530717959
2  8 9 0 4.71238898038469 6.28318530717959
0

0101000
+159 61 -157 61 *
Ed
 1.00000000030201e-05 1 1 0
1  30 0 -5.8 0
2  9 9 0 -5.8 0
0

0101000
+170 61 -157 61 *
Wi

0101100
+169 50 +171 50 +160 51 -158 50 -156 50 +155 50 *
Fa
0  1e-07 9 50

0111000
+154 0 *
Ve
1.00000000030201e-05
-5 -30.25 2.67903925355046e-15
0 0

0101101
*
Ve
1.00000000030201e-05
-5 -24.075 6.00970832742593e-15
0 0

0101101
*
Ed
 1.00000000030201e-05 1 1 0
1  6 0 29.75 35.925
0

0101000
+152 16 -151 16 *
Ve
1.00000000030201e-05
-5 -24.075 -3.69999999999999
0 0

0101101
*
Ed
 1.50000014528149e-07 1 1 0
1  31 0 -2.77499999999999 0.925000000000001
2  15 11 55 -2.77499999999999 0.925000000000001
2  16 3 9 -2.77499999999999 0.925000000000001
0

0101000
+149 0 -151 0 *
Ve
1.00000000030201e-05
-5 -30.25 -3.7
0 0

0101101
*
Ed
 1.00000000030201e-05 1 1 0
1  6 0 29.75 35.925
0

0101000
+147 18 -149 18 *
Ed
 1.50000014528149e-07 1 1 0
1  32 0 -0.925000000000003 2.77499999999999
2  17 12 67 -0.925000000000003 2.77499999999999
2  18 3 9 -0.925000000000003 2.77499999999999
0

0101000
+152 0 -147 0 *
Wi

0101100
-150 15 +148 0 +146 17 +145 0 *
Fa
0  1e-07 3 9

0101000
+144 0 *
Ed
 1.00000000030201e-05 1 1 0
1  33 0 0 2.05000000000001
0

0101000
+161 69 -151 70 *
Ed
 1.00000000030201e-05 1 1 0
1  34 0 0.999999999999988 3.05
0

0101000
+149 70 -157 69 *
Wi

0101100
-142 68 +148 0 -141 68 +156 60 +158 60 *
Ve
1e-07
3.10000000000001 35.925 -1.19114015465947e-14
0 0

0101101
*
Ed
 1e-07 1 1 0
1  35 0 0 6.28318530717959
2  14 10 59 0 6.28318530717959
0

0101100
+139 69 -139 69 *
Wi

0101100
-138 68 *
Fa
0  1.00000014528149e-07 11 55

0101000
+140 0 +137 0 *
Ve
1.00000000045097e-05
2.05000000000001 29.75 -1.85000000000001
0 0

0101101
*
Ve
1.00000015523806e-07
3.90000000000001 29.75 -7.13612604039733e-15
0 0

0101101
*
Ed
 1.00000014528149e-07 1 1 0
1  36 0 3.14159265358979 4.71238898038469
2  3 13 0 3.14159265358979 4.71238898038469
0

0101000
+135 72 -134 72 *
Ve
1.00000000030201e-05
2.05000000000001 29.75 1.84999999999999
0 0

0101101
*
Ed
 1.00000014528149e-07 1 1 0
1  37 0 4.71238898038469 6.28318530717959
2  4 13 0 4.71238898038469 6.28318530717959
0

0101000
+134 72 -132 72 *
Ed
 1.00000000030201e-05 1 1 0
1  38 0 0.999999999999992 3.05
0

0101000
+147 74 -132 75 *
Ed
 1.00000000030201e-05 1 1 0
1  39 0 0 2.05000000000001
0

0101000
+135 75 -152 74 *
Wi

0101100
-133 71 -131 71 +130 73 +145 0 +129 73 *
Ve
1e-07
3.10000000000001 29.75 -5.3472079134985e-15
0 0

0101101
*
Ed
 1e-07 1 1 0
1  40 0 0 6.28318530717959
2  5 14 49 0 6.28318530717959
0

0101100
+127 75 -127 75 *
Wi

0101100
+126 73 *
Fa
0  1.00000014528149e-07 12 67

0101000
+128 0 +125 0 *
Ve
1.00000000034309e-05
2.05000000000001 23.95 -1.85000000000001
0 0

0101101
*
Ed
 1.00000000030201e-05 1 1 0
1  41 0 0 5.8
2  6 13 52 0 5.8
0

0101000
+123 76 -135 76 *
Ve
1.00000014528149e-07
3.90000000000001 23.95 -8.37806601716951e-15
0 0

0101101
*
Ed
 1.00000014528149e-07 1 1 0
1  42 0 3.14159265358979 4.71238898038469
2  7 13 0 3.14159265358979 4.71238898038469
0

0101000
+123 72 -121 72 *
Ve
1.00000000030201e-05
2.05000000000001 23.95 1.84999999999999
0 0

0101101
*
Ed
 1.00000014528149e-07 1 1 0
1  43 0 4.71238898038469 6.28318530717959
2  8 13 0 4.71238898038469 6.28318530717959
0

0101000
+121 72 -119 72 *
Ed
 1.00000000030201e-05 1 1 0
1  44 0 -5.8 0
2  9 13 0 -5.8 0
0

0101000
+132 72 -119 72 *
Wi

0101100
+131 50 +133 50 +122 51 -120 50 -118 50 +117 50 *
Fa
0  1e-07 13 50

0111000
+116 0 *
Ve
1.00000015523806e-07
3.9 5.8 8.40826391534412e-16
0 0

0101101
*
Ve
1.00000000030201e-05
2.05 5.8 1.85
0 0

0101101
*
Ed
 1.00000014528149e-07 1 1 0
1  45 0 4.71238898038469 6.28318530717959
2  4 15 0 4.71238898038469 6.28318530717959
0

0101000
+114 79 -113 79 *
Ve
1.00000000045097e-05
2.05 5.8 -1.85
0 0

0101101
*
Ed
 1.00000014528149e-07 1 1 0
1  46 0 3.14159265358979 4.71238898038469
2  3 15 0 3.14159265358979 4.71238898038469
0

0101000
+111 79 -114 79 *
Ve
1.00000000034309e-05
2.05 -3.28692043842088e-32 -1.85
0 0

0101101
*
Ed
 1.00000000030201e-05 1 1 0
1  47 0 0 5.8
2  6 15 52 0 5.8
0

0101000
+109 80 -111 80 *
Ve
1.00000000030201e-05
3.9 -4.01113585237762e-16 -4.01113585237762e-16
0 0

0101101
*
Ed
 1.00000000030201e-05 1 1 0
1  48 0 3.14159265358979 4.71238898038469
2  7 15 0 3.14159265358979 4.71238898038469
0

0101000
+109 79 -107 79 *
Ve
1.00000000030201e-05
2.05 -4.10782519111308e-16 1.85
0 0

0101101
*
Ed
 1.00000000030201e-05 1 1 0
1  49 0 4.71238898038469 6.28318530717959
2  8 15 0 4.71238898038469 6.28318530717959
0

0101000
+107 79 -105 79 *
Ed
 1.00000000030201e-05 1 1 0
1  50 0 -5.8 0
2  9 15 0 -5.8 0
0

0101000
+113 79 -105 79 *
Wi

0101100
+112 50 +110 50 +108 51 -106 50 -104 50 +103 50 *
Fa
0  1e-07 15 50

0111000
+102 0 *
Ve
1.00000000030201e-05
-5 -54.2 -3.7
0 0

0101101
*
Ed
 1.00000000030201e-05 1 1 0
1  51 0 1 3.05
0

0101000
+100 83 -113 84 *
Ve
1.00000000030201e-05
-5 -54.2 -1.3177636351001e-15
0 0

0101101
*
Ed
 1.50000014528149e-07 1 1 0
1  52 0 -0.925000000000002 2.775
2  19 16 78 -0.925000000000002 2.775
2  20 3 9 -0.925000000000002 2.775
0

0101000
+98 0 -100 0 *
Ed
 1.00000000030201e-05 1 1 0
1  53 0 0 2.05
0

0101000
+111 84 -98 83 *
Wi

0101100
-110 81 -112 81 +99 82 +97 0 +96 82 *
Ve
1e-07
3.1 5.8 2.62974451843325e-15
0 0

0101101
*
Ed
 1e-07 1 1 0
1  54 0 0 6.28318530717959
2  5 17 49 0 6.28318530717959
0

0101100
+94 84 -94 84 *
Wi

0101100
+93 82 *
Fa
0  1.00000014528149e-07 16 78

0101000
+95 0 +92 0 *
Ve
1.00000000030201e-05
-5 -48.025 2.01290543877537e-15
0 0

0101101
*
Ed
 1.00000000030201e-05 1 1 0
1  6 0 5.8 11.975
0

0101000
+98 16 -90 16 *
Ve
1.00000000030201e-05
-5 -48.025 -3.7
0 0

0101101
*
Ed
 1.50000014528149e-07 1 1 0
1  55 0 -2.775 0.925000000000001
2  21 18 86 -2.775 0.925000000000001
2  22 3 9 -2.775 0.925000000000001
0

0101000
+88 0 -90 0 *
Ed
 1.00000000030201e-05 1 1 0
1  6 0 5.8 11.975
0

0101000
+100 18 -88 18 *
Wi

0101100
-89 15 +87 0 +86 17 +97 0 *
Fa
0  1e-07 3 9

0101000
+85 0 *
Ve
1e-07
3.1 -2.39928527280864e-32 5.40271013028825e-17
0 0

0101101
*
Ed
 1e-07 1 1 0
1  56 0 0 5.8
3  23 24CN 17 0 0 5.8
0

0101000
+83 80 -94 80 *
Ed
 1e-07 1 1 0
1  57 0 0 6.28318530717959
2  14 17 59 0 6.28318530717959
0

0101100
+83 89 -83 89 *
Wi

0101100
+82 0 -82 0 -81 88 +93 90 *
Fa
0  1e-07 17 0

0111000
+80 0 *
Ve
1.00000000034309e-05
2.05 11.975 -1.85
0 0

0101101
*
Ed
 1.00000000030201e-05 1 1 0
1  58 0 0 2.05
0

0101000
+78 92 -90 93 *
Ve
1.00000000030201e-05
2.05 11.975 1.85
0 0

0101101
*
Ed
 1.00000000030201e-05 1 1 0
1  59 0 0.999999999999996 3.05
0

0101000
+88 93 -76 92 *
Ve
1.00000014528149e-07
3.9 11.975 -4.38958980120363e-15
0 0

0101101
*
Ed
 1.00000014528149e-07 1 1 0
1  60 0 4.71238898038469 6.28318530717959
2  8 19 0 4.71238898038469 6.28318530717959
0

0101000
+74 95 -76 95 *
Ed
 1.00000014528149e-07 1 1 0
1  61 0 3.14159265358979 4.71238898038469
2  7 19 0 3.14159265358979 4.71238898038469
0

0101000
+78 95 -74 95 *
Wi

0101100
-77 91 +87 0 -75 91 +73 94 +72 94 *
Ve
1e-07
3.1 11.975 -3.93444911466299e-15
0 0

0101101
*
Ed
 1e-07 1 1 0
1  62 0 0 6.28318530717959
2  14 20 59 0 6.28318530717959
0

0101100
+70 92 -70 92 *
Wi

0101100
-69 91 *
Fa
0  1.00000014528149e-07 18 86

0101000
+71 0 +68 0 *
Ve
1.00000015523806e-07
3.9 17.775 -3.14764982443146e-15
0 0

0101101
*
Ve
1.00000000030201e-05
2.05 17.775 1.85
0 0

0101101
*
Ed
 1.00000014528149e-07 1 1 0
1  63 0 4.71238898038469 6.28318530717959
2  4 19 0 4.71238898038469 6.28318530717959
0

0101000
+66 95 -65 95 *
Ve
1.00000000045097e-05
2.05 17.775 -1.85
0 0

0101101
*
Ed
 1.00000014528149e-07 1 1 0
1  64 0 3.14159265358979 4.71238898038469
2  3 19 0 3.14159265358979 4.71238898038469
0

0101000
+63 95 -66 95 *
Ed
 1.00000000030201e-05 1 1 0
1  65 0 0 5.8
2  6 19 52 0 5.8
0

0101000
+78 96 -63 96 *
Ed
 1.00000000030201e-05 1 1 0
1  66 0 -5.8 0
2  9 19 0 -5.8 0
0

0101000
+65 95 -76 95 *
Wi

0101100
+64 50 +62 50 +61 51 -72 50 -73 50 +60 50 *
Fa
0  1e-07 19 50

0111000
+59 0 *
Ve
1e-07
3.1 17.775 -1.35873169753263e-15
0 0

0101101
*
Ed
 1e-07 1 1 0
1  67 0 0 5.8
3  23 24CN 20 0 0 5.8
0

0101000
+70 96 -57 96 *
Ed
 1e-07 1 1 0
1  68 0 0 6.28318530717959
2  5 20 49 0 6.28318530717959
0

0101100
+57 98 -57 98 *
Wi

0101100
+56 0 -56 0 -69 88 +55 90 *
Fa
0  1e-07 20 0

0111000
+54 0 *
Ve
1.00000000030201e-05
-5 -42.225 -3.7
0 0

0101101
*
Ed
 1.00000000030201e-05 1 1 0
1  69 0 0.999999999999996 3.05
0

0101000
+52 100 -65 98 *
Ve
1.00000000030201e-05
-5 -42.225 6.80637809225182e-16
0 0

0101101
*
Ed
 1.50000014528149e-07 1 1 0
1  70 0 -0.925000000000003 2.775
2  25 21 86 -0.925000000000003 2.775
2  26 3 9 -0.925000000000003 2.775
0

0101000
+50 0 -52 0 *
Ed
 1.00000000030201e-05 1 1 0
1  71 0 0 2.05
0

0101000
+63 98 -50 100 *
Wi

0101100
-62 94 -64 94 +51 99 +49 0 +48 99 *
Wi

0101100
+55 99 *
Fa
0  1.00000014528149e-07 21 86

0101000
+47 0 +46 0 *
Ve
1.00000000030201e-05
-5 -36.05 4.01130688310065e-15
0 0

0101101
*
Ed
 1.00000000030201e-05 1 1 0
1  6 0 17.775 23.95
0

0101000
+50 16 -44 16 *
Ve
1.00000000030201e-05
-5 -36.05 -3.7
0 0

0101101
*
Ed
 1.50000014528149e-07 1 1 0
1  72 0 -2.77499999999999 0.925000000000001
2  27 22 67 -2.77499999999999 0.925000000000001
2  28 3 9 -2.77499999999999 0.925000000000001
0

0101000
+42 0 -44 0 *
Ed
 1.00000000030201e-05 1 1 0
1  6 0 17.775 23.95
0

0101000
+52 18 -42 18 *
Wi

0101100
-43 15 +41 0 +40 17 +49 0 *
Fa
0  1e-07 3 9

0101000
+39 0 *
Ed
 1.00000000030201e-05 1 1 0
1  73 0 0 2.05000000000001
0

0101000
+123 102 -44 103 *
Ed
 1.00000000030201e-05 1 1 0
1  74 0 0.999999999999992 3.05
0

0101000
+42 103 -119 102 *
Wi

0101100
-37 101 +41 0 -36 101 +118 71 +120 71 *
Ve
1e-07
3.10000000000001 23.95 -7.92292533062886e-15
0 0

0101101
*
Ed
 1e-07 1 1 0
1  75 0 0 6.28318530717959
2  14 14 59 0 6.28318530717959
0

0101100
+34 102 -34 102 *
Wi

0101100
-33 101 *
Fa
0  1.00000014528149e-07 22 67

0101000
+35 0 +32 0 *
Ed
 1e-07 1 1 0
1  76 0 0 5.8
3  23 24CN 14 0 0 5.8
0

0101000
+34 76 -127 76 *
Wi

0101100
+30 0 -30 0 -33 88 +126 90 *
Fa
0  1e-07 14 0

0111000
+29 0 *
Ed
 1e-07 1 1 0
1  77 0 0 5.8
3  23 24CN 10 0 0 5.8
0

0101000
+139 65 -165 65 *
Wi

0101100
+27 0 -27 0 -138 88 +164 90 *
Fa
0  1e-07 10 0

0111000
+26 0 *
Ed
 1e-07 1 1 0
1  78 0 0 5.8
3  23 24CN 6 0 0 5.8
0

0101000
+177 53 -203 53 *
Wi

0101100
+24 0 -24 0 -176 88 +202 90 *
Fa
0  1e-07 6 0

0111000
+23 0 *
Ed
 1e-07 1 1 0
1  79 0 0 12.05
0

0101000
+109 107 -223 15 *
Wi

0101000
+21 0 -221 15 -226 15 -217 15 -205 46 -198 106 +180 56 -188 15 -167 62 -160 105 
+142 68 -150 15 -129 73 -122 104 +37 101 -43 15 -48 99 -61 97 +77 91 -89 15 
-96 82 -108 87 *
Ve
1e-07
1.85 -4.53119315684521e-16 0
0 0

0101101
*
Ed
 1e-07 1 1 0
1  80 0 0 6.28318530717959
2  29 24 0 0 6.28318530717959
2  30 25 0 0 6.28318530717959
2  31 25 110 0 6.28318530717959
0

0101000
+19 0 -19 0 *
Wi

0101100
-18 108 *
Fa
0  1.00000000030201e-05 23 0

0101000
+20 0 +17 0 *
Ve
1e-07
1.85 -4.53119315684521e-16 0
0 0

0101101
*
Ed
 1e-07 1 1 0
1  81 0 0 2
3  32 33CN 25 0 0 2
0

0101000
+19 0 -15 109 *
Ed
 1e-07 1 1 0
1  80 0 0 6.28318530717959
2  29 24 0 0 6.28318530717959
2  30 25 0 0 6.28318530717959
2  31 25 110 0 6.28318530717959
0

0101000
+15 0 -15 0 *
Wi

0101100
+14 0 -14 0 -18 0 +13 109 *
Fa
0  1e-07 25 0

0111000
+12 0 *
Wi

0101100
-13 0 *
Fa
0  1e-07 24 0

0111000
-10 0 *
Ed
 1e-07 1 1 0
1  82 0 -9 3.05
0

0101000
+223 17 -105 107 *
Wi

0101000
-21 0 +106 81 +104 81 -8 0 -222 9 *
Wi

0101100
-81 112 *
Fa
0  1.00000000030201e-05 26 0

0101000
+7 0 +6 0 *
Wi

0101000
+8 0 -103 81 -99 82 +86 17 +75 91 -60 94 -51 99 +40 17 +36 101 -117 71 
-130 73 +146 17 +141 68 -155 60 -168 62 +184 17 +179 56 -193 36 -206 46 +215 17 
+226 17 +221 17 *
Fa
0  1.00000000030201e-05 27 0

0101000
+4 0 *
Sh

0101000
-224 9 -219 9 -212 0 +200 0 +191 30 -181 0 +174 0 +162 0 +153 55 -143 0 
+136 0 +124 0 +115 67 +101 78 +91 0 -84 0 -79 87 +67 0 +58 86 -53 97 
+45 0 -38 0 +31 0 -28 104 -25 105 -22 106 +16 0 -11 108 +9 111 +5 0 
+3 0 *
So

1100000
+2 0 *

+1 1 ]]>
      </Part>
      <ElementMap new="1" count="1"><Element key="Dummy" value="Dummy"/></ElementMap>
      <ElementMap2 count="191">
<![CDATA[
2 PostfixCount 54
Edge
Face
Vertex
;:M#164;RFI;:He33:b,E
;:M#167;RFI;:He33:b,E
;:M#16a;RFI;:He33:b,F
;:M#16d;RFI;:He33:b,F
;:M#170;RFI;:He33:b,F
;:He33,V
;:He33,E
;:He33,F
;:He32,V
;:He32,E
;:He32,F
;:M2;FUS;:He33:8,E
;:M;FUS;:He33:7,F
;:G#13b;FUS;:He32:b,E
;:G2#141;FUS;:He32:c,E
;:G3#13d;FUS;:He32:c,E
;:G4#143;FUS;:He32:c,E
;:G5#140;FUS;:He32:c,E
;:G6#145;FUS;:He32:c,E
;:G7#142;FUS;:He32:c,E
;:G8#146;FUS;:He32:c,E
;:G9#144;FUS;:He32:c,E
;:M2;FUS;:He32:8,F
;:M3;FUS;:He32:8,F
;:M4;FUS;:He32:8,F
;:M5;FUS;:He32:8,F
;:M;FUS;:He32:7,F
;:M;FUS;:He33:7,E
;:G#153;FUS;:He32:b,V
;:G2#154;FUS;:He32:c,V
;:G3#156;FUS;:He32:c,V
;:G4#157;FUS;:He32:c,V
;:G5#158;FUS;:He32:c,V
;:G6#159;FUS;:He32:c,V
;:G7#15a;FUS;:He32:c,V
;:G8#15b;FUS;:He32:c,V
;:G9#15c;FUS;:He32:c,V
;:M10;FUS;:He32:9,E
;:M2;FUS;:He32:8,E
;:M4;FUS;:He32:8,E
;:M6;FUS;:He32:8,E
;:M8;FUS;:He32:8,E
;:G#152;FUS;:He32:b,V
;:G2#155;FUS;:He32:c,V
;:G3#15d;FUS;:He32:c,V
;:G4#15e;FUS;:He32:c,V
;:G5#15f;FUS;:He32:c,V
;:G6#160;FUS;:He32:c,V
;:G7#161;FUS;:He32:c,V
;:G8#162;FUS;:He32:c,V
;:G9#163;FUS;:He32:c,V

MapCount 1

ElementMap 1 2 3

Edge

ChildCount 0

NameCount 95
0
$#a5.d 0
$#a6.d 0
$#a7.d 0
$#a8.d 0
$#a9.d 0
$#aa.d 0
$#ab.d 0
$#bf.29 0
$#c0.29 0
$#bb.18.f0.146 0
$#8d.a 0
$#8c.a 0
$#e3.f 0
$#d7.1f 0
$#93.a 0
$#8e.a 0
$#8f.a 0
$#90.a 0
$#91.a 0
$#bf.2d 0
$#bb.19.ec.144 0
$#c0.2d 0
$#bb.16.ee.145 0
$#d5.1f 0
$#e1.f 0
$#95.a 0
$#77.a 0
$#76.a 0
$#e0.f 0
$#d3.1f 0
$#7d.a 0
$#78.a 0
$#79.a 0
$#7a.a 0
$#7b.a 0
$#bf.2c 0
$#bb.17.e8.142 0
$#c0.2c 0
$#bb.14.ea.143 0
$#d1.1f 0
$#de.f 0
$#7f.a 0
$#61.a 0
$#60.a 0
$#dd.f 0
$#cf.1f 0
$#67.a 0
$#62.a 0
$#63.a 0
$#64.a 0
$#65.a 0
$#2f.a 0
$#30.a 0
$#31.a 0
$#32.a 0
$#33.a 0
$#34.a 0
$#b8.f 0
$#bb.11.13b 0
$#bc.1f 0
$#3a.a 0
$#bf.2a 0
$#bb.13.c3.13d 0
$#c0.2a 0
$#3b.a 0
$#3c.a 0
$#c9.1f 0
$#d8.f 0
$#4e.a 0
$#4d.a 0
$#53.a 0
$#4a.a 0
$#4b.a 0
$#4c.a 0
$#4f.a 0
$#52.a 0
$#51.a 0
$#da.f 0
$#bb.12.e6.141 0
$#cb.1f 0
$#bf.2b 0
$#bb.15.e4.140 0
$#c0.2b 0
$#cd.1f 0
$#db.f 0
$#69.a 0
$#68.a 0
$#7e.a 0
$#94.a 0
$#166.4 0
$#ad.d 0
$#ae.d 0
$#b0.d 0
$#169.5 0

Face

ChildCount 0

NameCount 32
0
$#b2.e 0
$#b3.e 0
$#bb.1d.12 0
$#f0.10 0
$#96.b 0
$#bb.1c.12 0
$#ec.10 0
$#ee.10 0
$#80.b 0
$#bb.1b.12 0
$#e8.10 0
$#ea.10 0
$#6a.b 0
$#3d.b 0
$#b9.10 0
$#bb.1e.12 0
$#3f.b 0
$#c3.10 0
$#54.b 0
$#56.b 0
$#e6.10 0
$#bb.1a.12 0
$#e4.10 0
$#6c.b 0
$#82.b 0
$#98.b 0
$#16c.6 0
$#b5.e 0
$#b7.e 0
$#16f.7 0
$#172.8 0

Vertex

ChildCount 0

NameCount 67
0
$#9a.c 0
$#9b.c 0
$#9c.c 0
$#9d.c 0
$#9e.c 0
$#9f.c 0
$#bf.28.d7.15c 0
$#c0.36.e3.163 0
$#85.9 0
$#83.9 0
$#84.9 0
$#8a.9 0
$#86.9 0
$#87.9 0
$#88.9 0
$#bf.26.d3.15a 0
$#bf.27.d5.15b 0
$#c0.35.e1.162 0
$#c0.34.e0.161 0
$#8b.9 0
$#6f.9 0
$#6d.9 0
$#6e.9 0
$#74.9 0
$#70.9 0
$#71.9 0
$#72.9 0
$#bf.24.cf.158 0
$#bf.25.d1.159 0
$#c0.33.de.160 0
$#c0.32.dd.15f 0
$#75.9 0
$#59.9 0
$#57.9 0
$#58.9 0
$#5e.9 0
$#5a.9 0
$#5b.9 0
$#5c.9 0
$#24.9 0
$#25.9 0
$#26.9 0
$#27.9 0
$#28.9 0
$#29.9 0
$#c0.2e.b8.152 0
$#bf.20.bc.153 0
$#2d.9 0
$#bf.21.c9.154 0
$#c0.2f.d8.155 0
$#2e.9 0
$#44.9 0
$#46.9 0
$#45.9 0
$#49.9 0
$#41.9 0
$#42.9 0
$#43.9 0
$#48.9 0
$#c0.30.da.15d 0
$#bf.22.cb.156 0
$#bf.23.cd.157 0
$#c0.31.db.15e 0
$#5f.9 0
$#a1.c 0
$#a3.c 0

EndMap
]]>
      </ElementMap2>
    </Property>
    <Property name="Suppress" type="App::PropertyBool">
      <Bool value="false"/>
    </Property>
    <Property name="SuppressedShape" type="Part::PropertyPartShape">
      <Part ElementMap="0.15.70200.4" brep="1">
<![CDATA[

CASCADE Topology V1, (c) Matra-Datavision
Locations 0
Curve2ds 0
Curves 0
Polygon3D 0
PolygonOnTriangulations 0
Surfaces 0
Triangulations 0

TShapes 0

*]]>
      </Part>
      <ElementMap/>
    </Property>
    <Property name="TreeRank" type="App::PropertyInteger" status="2184">
      <Integer value="22"/>
    </Property>
    <Property name="Type" type="App::PropertyEnumeration">
      <Integer value="0"/>
    </Property>
    <Property name="ValidateShape" type="App::PropertyBool">
      <Bool value="true"/>
    </Property>
    <Property name="Visibility" type="App::PropertyBool" status="648">
      <Bool value="true"/>
    </Property>
    <Property name="_ExportChildren" type="App::PropertyLinkList" status="218104320">
      <LinkList count="2">
        <Link value="Reference"/>
        <Link value="Reference001"/>
      </LinkList>
    </Property>
    <Property name="_GroupVersion" type="App::PropertyInteger" status="218103808">
      <Integer value="1"/>
    </Property>
    <Property name="_Siblings" type="App::PropertyLinkList" status="218103808">
      <LinkList count="0">
      </LinkList>
    </Property>
  </Properties>
</Object>
</Document>
